{"identifier":{"url":"doc:\/\/com.SwiftyLab.HelperCoders\/documentation\/SwiftSyntaxBuilder\/SwiftSyntax","interfaceLanguage":"swift"},"topicSections":[{"anchor":"Extended-Protocols","title":"Extended Protocols","identifiers":["doc:\/\/com.SwiftyLab.HelperCoders\/documentation\/SwiftSyntaxBuilder\/SwiftSyntax\/SyntaxProtocol","doc:\/\/com.SwiftyLab.HelperCoders\/documentation\/SwiftSyntaxBuilder\/SwiftSyntax\/WithOptionalCodeBlockSyntax"],"generated":true},{"title":"Extended Structures","generated":true,"identifiers":["doc:\/\/com.SwiftyLab.HelperCoders\/documentation\/SwiftSyntaxBuilder\/SwiftSyntax\/AccessorBlockSyntax","doc:\/\/com.SwiftyLab.HelperCoders\/documentation\/SwiftSyntaxBuilder\/SwiftSyntax\/AccessorDeclListSyntax","doc:\/\/com.SwiftyLab.HelperCoders\/documentation\/SwiftSyntaxBuilder\/SwiftSyntax\/AccessorDeclSyntax","doc:\/\/com.SwiftyLab.HelperCoders\/documentation\/SwiftSyntaxBuilder\/SwiftSyntax\/ActorDeclSyntax","doc:\/\/com.SwiftyLab.HelperCoders\/documentation\/SwiftSyntaxBuilder\/SwiftSyntax\/ArrayElementListSyntax","doc:\/\/com.SwiftyLab.HelperCoders\/documentation\/SwiftSyntaxBuilder\/SwiftSyntax\/ArrayExprSyntax","doc:\/\/com.SwiftyLab.HelperCoders\/documentation\/SwiftSyntaxBuilder\/SwiftSyntax\/AssociatedTypeDeclSyntax","doc:\/\/com.SwiftyLab.HelperCoders\/documentation\/SwiftSyntaxBuilder\/SwiftSyntax\/AttributeListSyntax","doc:\/\/com.SwiftyLab.HelperCoders\/documentation\/SwiftSyntaxBuilder\/SwiftSyntax\/AttributeSyntax","doc:\/\/com.SwiftyLab.HelperCoders\/documentation\/SwiftSyntaxBuilder\/SwiftSyntax\/AvailabilityArgumentListSyntax","doc:\/\/com.SwiftyLab.HelperCoders\/documentation\/SwiftSyntaxBuilder\/SwiftSyntax\/BinaryOperatorExprSyntax","doc:\/\/com.SwiftyLab.HelperCoders\/documentation\/SwiftSyntaxBuilder\/SwiftSyntax\/BooleanLiteralExprSyntax","doc:\/\/com.SwiftyLab.HelperCoders\/documentation\/SwiftSyntaxBuilder\/SwiftSyntax\/CatchClauseListSyntax","doc:\/\/com.SwiftyLab.HelperCoders\/documentation\/SwiftSyntaxBuilder\/SwiftSyntax\/CatchClauseSyntax","doc:\/\/com.SwiftyLab.HelperCoders\/documentation\/SwiftSyntaxBuilder\/SwiftSyntax\/CatchItemListSyntax","doc:\/\/com.SwiftyLab.HelperCoders\/documentation\/SwiftSyntaxBuilder\/SwiftSyntax\/ClassDeclSyntax","doc:\/\/com.SwiftyLab.HelperCoders\/documentation\/SwiftSyntaxBuilder\/SwiftSyntax\/ClosureCaptureClauseSyntax","doc:\/\/com.SwiftyLab.HelperCoders\/documentation\/SwiftSyntaxBuilder\/SwiftSyntax\/ClosureCaptureListSyntax","doc:\/\/com.SwiftyLab.HelperCoders\/documentation\/SwiftSyntaxBuilder\/SwiftSyntax\/ClosureExprSyntax","doc:\/\/com.SwiftyLab.HelperCoders\/documentation\/SwiftSyntaxBuilder\/SwiftSyntax\/ClosureParameterListSyntax","doc:\/\/com.SwiftyLab.HelperCoders\/documentation\/SwiftSyntaxBuilder\/SwiftSyntax\/ClosureParameterSyntax","doc:\/\/com.SwiftyLab.HelperCoders\/documentation\/SwiftSyntaxBuilder\/SwiftSyntax\/ClosureShorthandParameterListSyntax","doc:\/\/com.SwiftyLab.HelperCoders\/documentation\/SwiftSyntaxBuilder\/SwiftSyntax\/CodeBlockItemListSyntax","doc:\/\/com.SwiftyLab.HelperCoders\/documentation\/SwiftSyntaxBuilder\/SwiftSyntax\/CodeBlockItemSyntax","doc:\/\/com.SwiftyLab.HelperCoders\/documentation\/SwiftSyntaxBuilder\/SwiftSyntax\/CodeBlockSyntax","doc:\/\/com.SwiftyLab.HelperCoders\/documentation\/SwiftSyntaxBuilder\/SwiftSyntax\/CompositionTypeElementListSyntax","doc:\/\/com.SwiftyLab.HelperCoders\/documentation\/SwiftSyntaxBuilder\/SwiftSyntax\/ConditionElementListSyntax","doc:\/\/com.SwiftyLab.HelperCoders\/documentation\/SwiftSyntaxBuilder\/SwiftSyntax\/DeclModifierListSyntax","doc:\/\/com.SwiftyLab.HelperCoders\/documentation\/SwiftSyntaxBuilder\/SwiftSyntax\/DeclNameArgumentListSyntax","doc:\/\/com.SwiftyLab.HelperCoders\/documentation\/SwiftSyntaxBuilder\/SwiftSyntax\/DeclSyntax","doc:\/\/com.SwiftyLab.HelperCoders\/documentation\/SwiftSyntaxBuilder\/SwiftSyntax\/DeferStmtSyntax","doc:\/\/com.SwiftyLab.HelperCoders\/documentation\/SwiftSyntaxBuilder\/SwiftSyntax\/DeinitializerDeclSyntax","doc:\/\/com.SwiftyLab.HelperCoders\/documentation\/SwiftSyntaxBuilder\/SwiftSyntax\/DesignatedTypeListSyntax","doc:\/\/com.SwiftyLab.HelperCoders\/documentation\/SwiftSyntaxBuilder\/SwiftSyntax\/DictionaryElementListSyntax","doc:\/\/com.SwiftyLab.HelperCoders\/documentation\/SwiftSyntaxBuilder\/SwiftSyntax\/DictionaryExprSyntax","doc:\/\/com.SwiftyLab.HelperCoders\/documentation\/SwiftSyntaxBuilder\/SwiftSyntax\/DifferentiabilityArgumentListSyntax","doc:\/\/com.SwiftyLab.HelperCoders\/documentation\/SwiftSyntaxBuilder\/SwiftSyntax\/DoStmtSyntax","doc:\/\/com.SwiftyLab.HelperCoders\/documentation\/SwiftSyntaxBuilder\/SwiftSyntax\/DocumentationAttributeArgumentListSyntax","doc:\/\/com.SwiftyLab.HelperCoders\/documentation\/SwiftSyntaxBuilder\/SwiftSyntax\/EffectsAttributeArgumentListSyntax","doc:\/\/com.SwiftyLab.HelperCoders\/documentation\/SwiftSyntaxBuilder\/SwiftSyntax\/EnumCaseDeclSyntax","doc:\/\/com.SwiftyLab.HelperCoders\/documentation\/SwiftSyntaxBuilder\/SwiftSyntax\/EnumCaseElementListSyntax","doc:\/\/com.SwiftyLab.HelperCoders\/documentation\/SwiftSyntaxBuilder\/SwiftSyntax\/EnumCaseParameterListSyntax","doc:\/\/com.SwiftyLab.HelperCoders\/documentation\/SwiftSyntaxBuilder\/SwiftSyntax\/EnumCaseParameterSyntax","doc:\/\/com.SwiftyLab.HelperCoders\/documentation\/SwiftSyntaxBuilder\/SwiftSyntax\/EnumDeclSyntax","doc:\/\/com.SwiftyLab.HelperCoders\/documentation\/SwiftSyntaxBuilder\/SwiftSyntax\/ExprListSyntax","doc:\/\/com.SwiftyLab.HelperCoders\/documentation\/SwiftSyntaxBuilder\/SwiftSyntax\/ExprSyntax","doc:\/\/com.SwiftyLab.HelperCoders\/documentation\/SwiftSyntaxBuilder\/SwiftSyntax\/ExpressionSegmentSyntax","doc:\/\/com.SwiftyLab.HelperCoders\/documentation\/SwiftSyntaxBuilder\/SwiftSyntax\/ExtensionDeclSyntax","doc:\/\/com.SwiftyLab.HelperCoders\/documentation\/SwiftSyntaxBuilder\/SwiftSyntax\/FloatLiteralExprSyntax","doc:\/\/com.SwiftyLab.HelperCoders\/documentation\/SwiftSyntaxBuilder\/SwiftSyntax\/ForStmtSyntax","doc:\/\/com.SwiftyLab.HelperCoders\/documentation\/SwiftSyntaxBuilder\/SwiftSyntax\/FunctionCallExprSyntax","doc:\/\/com.SwiftyLab.HelperCoders\/documentation\/SwiftSyntaxBuilder\/SwiftSyntax\/FunctionDeclSyntax","doc:\/\/com.SwiftyLab.HelperCoders\/documentation\/SwiftSyntaxBuilder\/SwiftSyntax\/FunctionParameterClauseSyntax","doc:\/\/com.SwiftyLab.HelperCoders\/documentation\/SwiftSyntaxBuilder\/SwiftSyntax\/FunctionParameterListSyntax","doc:\/\/com.SwiftyLab.HelperCoders\/documentation\/SwiftSyntaxBuilder\/SwiftSyntax\/FunctionParameterSyntax","doc:\/\/com.SwiftyLab.HelperCoders\/documentation\/SwiftSyntaxBuilder\/SwiftSyntax\/GenericArgumentClauseSyntax","doc:\/\/com.SwiftyLab.HelperCoders\/documentation\/SwiftSyntaxBuilder\/SwiftSyntax\/GenericArgumentListSyntax","doc:\/\/com.SwiftyLab.HelperCoders\/documentation\/SwiftSyntaxBuilder\/SwiftSyntax\/GenericParameterClauseSyntax","doc:\/\/com.SwiftyLab.HelperCoders\/documentation\/SwiftSyntaxBuilder\/SwiftSyntax\/GenericParameterListSyntax","doc:\/\/com.SwiftyLab.HelperCoders\/documentation\/SwiftSyntaxBuilder\/SwiftSyntax\/GenericRequirementListSyntax","doc:\/\/com.SwiftyLab.HelperCoders\/documentation\/SwiftSyntaxBuilder\/SwiftSyntax\/GenericWhereClauseSyntax","doc:\/\/com.SwiftyLab.HelperCoders\/documentation\/SwiftSyntaxBuilder\/SwiftSyntax\/GuardStmtSyntax","doc:\/\/com.SwiftyLab.HelperCoders\/documentation\/SwiftSyntaxBuilder\/SwiftSyntax\/IfConfigClauseListSyntax","doc:\/\/com.SwiftyLab.HelperCoders\/documentation\/SwiftSyntaxBuilder\/SwiftSyntax\/IfExprSyntax","doc:\/\/com.SwiftyLab.HelperCoders\/documentation\/SwiftSyntaxBuilder\/SwiftSyntax\/ImportDeclSyntax","doc:\/\/com.SwiftyLab.HelperCoders\/documentation\/SwiftSyntaxBuilder\/SwiftSyntax\/ImportPathComponentListSyntax","doc:\/\/com.SwiftyLab.HelperCoders\/documentation\/SwiftSyntaxBuilder\/SwiftSyntax\/InheritanceClauseSyntax","doc:\/\/com.SwiftyLab.HelperCoders\/documentation\/SwiftSyntaxBuilder\/SwiftSyntax\/InheritedTypeListSyntax","doc:\/\/com.SwiftyLab.HelperCoders\/documentation\/SwiftSyntaxBuilder\/SwiftSyntax\/InitializerDeclSyntax","doc:\/\/com.SwiftyLab.HelperCoders\/documentation\/SwiftSyntaxBuilder\/SwiftSyntax\/IntegerLiteralExprSyntax","doc:\/\/com.SwiftyLab.HelperCoders\/documentation\/SwiftSyntaxBuilder\/SwiftSyntax\/KeyPathComponentListSyntax","doc:\/\/com.SwiftyLab.HelperCoders\/documentation\/SwiftSyntaxBuilder\/SwiftSyntax\/KeyPathSubscriptComponentSyntax","doc:\/\/com.SwiftyLab.HelperCoders\/documentation\/SwiftSyntaxBuilder\/SwiftSyntax\/LabeledExprListSyntax","doc:\/\/com.SwiftyLab.HelperCoders\/documentation\/SwiftSyntaxBuilder\/SwiftSyntax\/LabeledExprSyntax","doc:\/\/com.SwiftyLab.HelperCoders\/documentation\/SwiftSyntaxBuilder\/SwiftSyntax\/MacroDeclSyntax","doc:\/\/com.SwiftyLab.HelperCoders\/documentation\/SwiftSyntaxBuilder\/SwiftSyntax\/MacroExpansionDeclSyntax","doc:\/\/com.SwiftyLab.HelperCoders\/documentation\/SwiftSyntaxBuilder\/SwiftSyntax\/MacroExpansionExprSyntax","doc:\/\/com.SwiftyLab.HelperCoders\/documentation\/SwiftSyntaxBuilder\/SwiftSyntax\/MemberBlockItemListSyntax","doc:\/\/com.SwiftyLab.HelperCoders\/documentation\/SwiftSyntaxBuilder\/SwiftSyntax\/MemberBlockSyntax","doc:\/\/com.SwiftyLab.HelperCoders\/documentation\/SwiftSyntaxBuilder\/SwiftSyntax\/MultipleTrailingClosureElementListSyntax","doc:\/\/com.SwiftyLab.HelperCoders\/documentation\/SwiftSyntaxBuilder\/SwiftSyntax\/ObjCSelectorPieceListSyntax","doc:\/\/com.SwiftyLab.HelperCoders\/documentation\/SwiftSyntaxBuilder\/SwiftSyntax\/OperatorDeclSyntax","doc:\/\/com.SwiftyLab.HelperCoders\/documentation\/SwiftSyntaxBuilder\/SwiftSyntax\/PatternBindingListSyntax","doc:\/\/com.SwiftyLab.HelperCoders\/documentation\/SwiftSyntaxBuilder\/SwiftSyntax\/PatternSyntax","doc:\/\/com.SwiftyLab.HelperCoders\/documentation\/SwiftSyntaxBuilder\/SwiftSyntax\/PlatformVersionItemListSyntax","doc:\/\/com.SwiftyLab.HelperCoders\/documentation\/SwiftSyntaxBuilder\/SwiftSyntax\/PrecedenceGroupAttributeListSyntax","doc:\/\/com.SwiftyLab.HelperCoders\/documentation\/SwiftSyntaxBuilder\/SwiftSyntax\/PrecedenceGroupDeclSyntax","doc:\/\/com.SwiftyLab.HelperCoders\/documentation\/SwiftSyntaxBuilder\/SwiftSyntax\/PrecedenceGroupNameListSyntax","doc:\/\/com.SwiftyLab.HelperCoders\/documentation\/SwiftSyntaxBuilder\/SwiftSyntax\/PrimaryAssociatedTypeListSyntax","doc:\/\/com.SwiftyLab.HelperCoders\/documentation\/SwiftSyntaxBuilder\/SwiftSyntax\/ProtocolDeclSyntax","doc:\/\/com.SwiftyLab.HelperCoders\/documentation\/SwiftSyntaxBuilder\/SwiftSyntax\/RepeatStmtSyntax","doc:\/\/com.SwiftyLab.HelperCoders\/documentation\/SwiftSyntaxBuilder\/SwiftSyntax\/SequenceExprSyntax","doc:\/\/com.SwiftyLab.HelperCoders\/documentation\/SwiftSyntaxBuilder\/SwiftSyntax\/SimpleStringLiteralSegmentListSyntax","doc:\/\/com.SwiftyLab.HelperCoders\/documentation\/SwiftSyntaxBuilder\/SwiftSyntax\/SourceFileSyntax","doc:\/\/com.SwiftyLab.HelperCoders\/documentation\/SwiftSyntaxBuilder\/SwiftSyntax\/SpecializeAttributeArgumentListSyntax","doc:\/\/com.SwiftyLab.HelperCoders\/documentation\/SwiftSyntaxBuilder\/SwiftSyntax\/StmtSyntax","doc:\/\/com.SwiftyLab.HelperCoders\/documentation\/SwiftSyntaxBuilder\/SwiftSyntax\/StringLiteralExprSyntax","doc:\/\/com.SwiftyLab.HelperCoders\/documentation\/SwiftSyntaxBuilder\/SwiftSyntax\/StringLiteralSegmentListSyntax","doc:\/\/com.SwiftyLab.HelperCoders\/documentation\/SwiftSyntaxBuilder\/SwiftSyntax\/StructDeclSyntax","doc:\/\/com.SwiftyLab.HelperCoders\/documentation\/SwiftSyntaxBuilder\/SwiftSyntax\/SubscriptCallExprSyntax","doc:\/\/com.SwiftyLab.HelperCoders\/documentation\/SwiftSyntaxBuilder\/SwiftSyntax\/SubscriptDeclSyntax","doc:\/\/com.SwiftyLab.HelperCoders\/documentation\/SwiftSyntaxBuilder\/SwiftSyntax\/SwitchCaseItemListSyntax","doc:\/\/com.SwiftyLab.HelperCoders\/documentation\/SwiftSyntaxBuilder\/SwiftSyntax\/SwitchCaseLabelSyntax","doc:\/\/com.SwiftyLab.HelperCoders\/documentation\/SwiftSyntaxBuilder\/SwiftSyntax\/SwitchCaseListSyntax","doc:\/\/com.SwiftyLab.HelperCoders\/documentation\/SwiftSyntaxBuilder\/SwiftSyntax\/SwitchCaseSyntax","doc:\/\/com.SwiftyLab.HelperCoders\/documentation\/SwiftSyntaxBuilder\/SwiftSyntax\/SwitchExprSyntax","doc:\/\/com.SwiftyLab.HelperCoders\/documentation\/SwiftSyntaxBuilder\/SwiftSyntax\/TokenSyntax","doc:\/\/com.SwiftyLab.HelperCoders\/documentation\/SwiftSyntaxBuilder\/SwiftSyntax\/Trivia","doc:\/\/com.SwiftyLab.HelperCoders\/documentation\/SwiftSyntaxBuilder\/SwiftSyntax\/TupleExprSyntax","doc:\/\/com.SwiftyLab.HelperCoders\/documentation\/SwiftSyntaxBuilder\/SwiftSyntax\/TuplePatternElementListSyntax","doc:\/\/com.SwiftyLab.HelperCoders\/documentation\/SwiftSyntaxBuilder\/SwiftSyntax\/TuplePatternSyntax","doc:\/\/com.SwiftyLab.HelperCoders\/documentation\/SwiftSyntaxBuilder\/SwiftSyntax\/TupleTypeElementListSyntax","doc:\/\/com.SwiftyLab.HelperCoders\/documentation\/SwiftSyntaxBuilder\/SwiftSyntax\/TypeAliasDeclSyntax","doc:\/\/com.SwiftyLab.HelperCoders\/documentation\/SwiftSyntaxBuilder\/SwiftSyntax\/TypeSpecifierListSyntax","doc:\/\/com.SwiftyLab.HelperCoders\/documentation\/SwiftSyntaxBuilder\/SwiftSyntax\/TypeSyntax","doc:\/\/com.SwiftyLab.HelperCoders\/documentation\/SwiftSyntaxBuilder\/SwiftSyntax\/UnexpectedNodesSyntax","doc:\/\/com.SwiftyLab.HelperCoders\/documentation\/SwiftSyntaxBuilder\/SwiftSyntax\/VariableDeclSyntax","doc:\/\/com.SwiftyLab.HelperCoders\/documentation\/SwiftSyntaxBuilder\/SwiftSyntax\/VersionComponentListSyntax","doc:\/\/com.SwiftyLab.HelperCoders\/documentation\/SwiftSyntaxBuilder\/SwiftSyntax\/VersionTupleSyntax","doc:\/\/com.SwiftyLab.HelperCoders\/documentation\/SwiftSyntaxBuilder\/SwiftSyntax\/WhileStmtSyntax","doc:\/\/com.SwiftyLab.HelperCoders\/documentation\/SwiftSyntaxBuilder\/SwiftSyntax\/YieldedExpressionListSyntax"],"anchor":"Extended-Structures"}],"variants":[{"paths":["\/documentation\/swiftsyntaxbuilder\/swiftsyntax"],"traits":[{"interfaceLanguage":"swift"}]}],"schemaVersion":{"minor":3,"patch":0,"major":0},"metadata":{"symbolKind":"extension","externalID":"s:m:s:e:s:11SwiftSyntax010ImportDeclB0Vs:18SwiftSyntaxBuilder04DeclB9ParseableP","title":"SwiftSyntax","modules":[{"name":"SwiftSyntaxBuilder"}],"role":"collection","roleHeading":"Extended Module"},"kind":"symbol","sections":[],"hierarchy":{"paths":[["doc:\/\/com.SwiftyLab.HelperCoders\/documentation\/SwiftSyntaxBuilder"]]},"references":{"doc://com.SwiftyLab.HelperCoders/documentation/SwiftSyntaxBuilder/SwiftSyntax/AttributeSyntax":{"abstract":[],"kind":"symbol","url":"\/documentation\/swiftsyntaxbuilder\/swiftsyntax\/attributesyntax","navigatorTitle":[{"kind":"identifier","text":"AttributeSyntax"}],"title":"AttributeSyntax","identifier":"doc:\/\/com.SwiftyLab.HelperCoders\/documentation\/SwiftSyntaxBuilder\/SwiftSyntax\/AttributeSyntax","fragments":[{"kind":"keyword","text":"extension"},{"text":" ","kind":"text"},{"preciseIdentifier":"s:11SwiftSyntax09AttributeB0V","text":"AttributeSyntax","kind":"identifier"}],"type":"topic","role":"symbol"},"doc://com.SwiftyLab.HelperCoders/documentation/SwiftSyntaxBuilder/SwiftSyntax/TuplePatternElementListSyntax":{"abstract":[],"type":"topic","identifier":"doc:\/\/com.SwiftyLab.HelperCoders\/documentation\/SwiftSyntaxBuilder\/SwiftSyntax\/TuplePatternElementListSyntax","title":"TuplePatternElementListSyntax","navigatorTitle":[{"kind":"identifier","text":"TuplePatternElementListSyntax"}],"kind":"symbol","role":"symbol","fragments":[{"kind":"keyword","text":"extension"},{"kind":"text","text":" "},{"preciseIdentifier":"s:11SwiftSyntax023TuplePatternElementListB0V","text":"TuplePatternElementListSyntax","kind":"identifier"}],"url":"\/documentation\/swiftsyntaxbuilder\/swiftsyntax\/tuplepatternelementlistsyntax"},"doc://com.SwiftyLab.HelperCoders/documentation/SwiftSyntaxBuilder/SwiftSyntax/DifferentiabilityArgumentListSyntax":{"type":"topic","role":"symbol","navigatorTitle":[{"text":"DifferentiabilityArgumentListSyntax","kind":"identifier"}],"title":"DifferentiabilityArgumentListSyntax","fragments":[{"kind":"keyword","text":"extension"},{"text":" ","kind":"text"},{"text":"DifferentiabilityArgumentListSyntax","preciseIdentifier":"s:11SwiftSyntax029DifferentiabilityArgumentListB0V","kind":"identifier"}],"identifier":"doc:\/\/com.SwiftyLab.HelperCoders\/documentation\/SwiftSyntaxBuilder\/SwiftSyntax\/DifferentiabilityArgumentListSyntax","abstract":[],"kind":"symbol","url":"\/documentation\/swiftsyntaxbuilder\/swiftsyntax\/differentiabilityargumentlistsyntax"},"doc://com.SwiftyLab.HelperCoders/documentation/SwiftSyntaxBuilder/SwiftSyntax/FloatLiteralExprSyntax":{"type":"topic","fragments":[{"kind":"keyword","text":"extension"},{"text":" ","kind":"text"},{"text":"FloatLiteralExprSyntax","kind":"identifier","preciseIdentifier":"s:11SwiftSyntax016FloatLiteralExprB0V"}],"role":"symbol","abstract":[],"kind":"symbol","navigatorTitle":[{"kind":"identifier","text":"FloatLiteralExprSyntax"}],"title":"FloatLiteralExprSyntax","identifier":"doc:\/\/com.SwiftyLab.HelperCoders\/documentation\/SwiftSyntaxBuilder\/SwiftSyntax\/FloatLiteralExprSyntax","url":"\/documentation\/swiftsyntaxbuilder\/swiftsyntax\/floatliteralexprsyntax"},"doc://com.SwiftyLab.HelperCoders/documentation/SwiftSyntaxBuilder/SwiftSyntax/ExprSyntax":{"kind":"symbol","title":"ExprSyntax","type":"topic","abstract":[],"navigatorTitle":[{"text":"ExprSyntax","kind":"identifier"}],"url":"\/documentation\/swiftsyntaxbuilder\/swiftsyntax\/exprsyntax","identifier":"doc:\/\/com.SwiftyLab.HelperCoders\/documentation\/SwiftSyntaxBuilder\/SwiftSyntax\/ExprSyntax","role":"symbol","fragments":[{"text":"extension","kind":"keyword"},{"text":" ","kind":"text"},{"kind":"identifier","preciseIdentifier":"s:11SwiftSyntax04ExprB0V","text":"ExprSyntax"}]},"doc://com.SwiftyLab.HelperCoders/documentation/SwiftSyntaxBuilder/SwiftSyntax/OperatorDeclSyntax":{"identifier":"doc:\/\/com.SwiftyLab.HelperCoders\/documentation\/SwiftSyntaxBuilder\/SwiftSyntax\/OperatorDeclSyntax","title":"OperatorDeclSyntax","type":"topic","abstract":[],"role":"symbol","url":"\/documentation\/swiftsyntaxbuilder\/swiftsyntax\/operatordeclsyntax","fragments":[{"text":"extension","kind":"keyword"},{"kind":"text","text":" "},{"kind":"identifier","text":"OperatorDeclSyntax","preciseIdentifier":"s:11SwiftSyntax012OperatorDeclB0V"}],"navigatorTitle":[{"text":"OperatorDeclSyntax","kind":"identifier"}],"kind":"symbol"},"doc://com.SwiftyLab.HelperCoders/documentation/SwiftSyntaxBuilder/SwiftSyntax/EnumCaseElementListSyntax":{"url":"\/documentation\/swiftsyntaxbuilder\/swiftsyntax\/enumcaseelementlistsyntax","title":"EnumCaseElementListSyntax","fragments":[{"kind":"keyword","text":"extension"},{"text":" ","kind":"text"},{"text":"EnumCaseElementListSyntax","kind":"identifier","preciseIdentifier":"s:11SwiftSyntax019EnumCaseElementListB0V"}],"role":"symbol","kind":"symbol","identifier":"doc:\/\/com.SwiftyLab.HelperCoders\/documentation\/SwiftSyntaxBuilder\/SwiftSyntax\/EnumCaseElementListSyntax","abstract":[],"type":"topic","navigatorTitle":[{"text":"EnumCaseElementListSyntax","kind":"identifier"}]},"doc://com.SwiftyLab.HelperCoders/documentation/SwiftSyntaxBuilder/SwiftSyntax/EnumCaseParameterListSyntax":{"identifier":"doc:\/\/com.SwiftyLab.HelperCoders\/documentation\/SwiftSyntaxBuilder\/SwiftSyntax\/EnumCaseParameterListSyntax","kind":"symbol","url":"\/documentation\/swiftsyntaxbuilder\/swiftsyntax\/enumcaseparameterlistsyntax","abstract":[],"fragments":[{"kind":"keyword","text":"extension"},{"text":" ","kind":"text"},{"kind":"identifier","text":"EnumCaseParameterListSyntax","preciseIdentifier":"s:11SwiftSyntax021EnumCaseParameterListB0V"}],"role":"symbol","navigatorTitle":[{"kind":"identifier","text":"EnumCaseParameterListSyntax"}],"type":"topic","title":"EnumCaseParameterListSyntax"},"doc://com.SwiftyLab.HelperCoders/documentation/SwiftSyntaxBuilder/SwiftSyntax/MacroExpansionDeclSyntax":{"fragments":[{"text":"extension","kind":"keyword"},{"text":" ","kind":"text"},{"text":"MacroExpansionDeclSyntax","preciseIdentifier":"s:11SwiftSyntax018MacroExpansionDeclB0V","kind":"identifier"}],"navigatorTitle":[{"kind":"identifier","text":"MacroExpansionDeclSyntax"}],"type":"topic","title":"MacroExpansionDeclSyntax","url":"\/documentation\/swiftsyntaxbuilder\/swiftsyntax\/macroexpansiondeclsyntax","role":"symbol","kind":"symbol","abstract":[],"identifier":"doc:\/\/com.SwiftyLab.HelperCoders\/documentation\/SwiftSyntaxBuilder\/SwiftSyntax\/MacroExpansionDeclSyntax"},"doc://com.SwiftyLab.HelperCoders/documentation/SwiftSyntaxBuilder/SwiftSyntax/DeclSyntax":{"role":"symbol","kind":"symbol","navigatorTitle":[{"kind":"identifier","text":"DeclSyntax"}],"title":"DeclSyntax","identifier":"doc:\/\/com.SwiftyLab.HelperCoders\/documentation\/SwiftSyntaxBuilder\/SwiftSyntax\/DeclSyntax","abstract":[],"fragments":[{"text":"extension","kind":"keyword"},{"kind":"text","text":" "},{"preciseIdentifier":"s:11SwiftSyntax04DeclB0V","kind":"identifier","text":"DeclSyntax"}],"url":"\/documentation\/swiftsyntaxbuilder\/swiftsyntax\/declsyntax","type":"topic"},"doc://com.SwiftyLab.HelperCoders/documentation/SwiftSyntaxBuilder/SwiftSyntax/CatchClauseListSyntax":{"identifier":"doc:\/\/com.SwiftyLab.HelperCoders\/documentation\/SwiftSyntaxBuilder\/SwiftSyntax\/CatchClauseListSyntax","title":"CatchClauseListSyntax","navigatorTitle":[{"kind":"identifier","text":"CatchClauseListSyntax"}],"url":"\/documentation\/swiftsyntaxbuilder\/swiftsyntax\/catchclauselistsyntax","type":"topic","abstract":[],"fragments":[{"text":"extension","kind":"keyword"},{"kind":"text","text":" "},{"text":"CatchClauseListSyntax","kind":"identifier","preciseIdentifier":"s:11SwiftSyntax015CatchClauseListB0V"}],"role":"symbol","kind":"symbol"},"doc://com.SwiftyLab.HelperCoders/documentation/SwiftSyntaxBuilder/SwiftSyntax/PatternSyntax":{"navigatorTitle":[{"kind":"identifier","text":"PatternSyntax"}],"identifier":"doc:\/\/com.SwiftyLab.HelperCoders\/documentation\/SwiftSyntaxBuilder\/SwiftSyntax\/PatternSyntax","abstract":[],"type":"topic","fragments":[{"text":"extension","kind":"keyword"},{"kind":"text","text":" "},{"kind":"identifier","text":"PatternSyntax","preciseIdentifier":"s:11SwiftSyntax07PatternB0V"}],"url":"\/documentation\/swiftsyntaxbuilder\/swiftsyntax\/patternsyntax","kind":"symbol","role":"symbol","title":"PatternSyntax"},"doc://com.SwiftyLab.HelperCoders/documentation/SwiftSyntaxBuilder/SwiftSyntax/StringLiteralSegmentListSyntax":{"title":"StringLiteralSegmentListSyntax","identifier":"doc:\/\/com.SwiftyLab.HelperCoders\/documentation\/SwiftSyntaxBuilder\/SwiftSyntax\/StringLiteralSegmentListSyntax","kind":"symbol","url":"\/documentation\/swiftsyntaxbuilder\/swiftsyntax\/stringliteralsegmentlistsyntax","type":"topic","navigatorTitle":[{"text":"StringLiteralSegmentListSyntax","kind":"identifier"}],"role":"symbol","fragments":[{"kind":"keyword","text":"extension"},{"text":" ","kind":"text"},{"text":"StringLiteralSegmentListSyntax","kind":"identifier","preciseIdentifier":"s:11SwiftSyntax024StringLiteralSegmentListB0V"}],"abstract":[]},"doc://com.SwiftyLab.HelperCoders/documentation/SwiftSyntaxBuilder/SwiftSyntax/ObjCSelectorPieceListSyntax":{"abstract":[],"identifier":"doc:\/\/com.SwiftyLab.HelperCoders\/documentation\/SwiftSyntaxBuilder\/SwiftSyntax\/ObjCSelectorPieceListSyntax","title":"ObjCSelectorPieceListSyntax","url":"\/documentation\/swiftsyntaxbuilder\/swiftsyntax\/objcselectorpiecelistsyntax","kind":"symbol","role":"symbol","fragments":[{"text":"extension","kind":"keyword"},{"text":" ","kind":"text"},{"preciseIdentifier":"s:11SwiftSyntax021ObjCSelectorPieceListB0V","text":"ObjCSelectorPieceListSyntax","kind":"identifier"}],"navigatorTitle":[{"kind":"identifier","text":"ObjCSelectorPieceListSyntax"}],"type":"topic"},"doc://com.SwiftyLab.HelperCoders/documentation/SwiftSyntaxBuilder/SwiftSyntax/DoStmtSyntax":{"kind":"symbol","identifier":"doc:\/\/com.SwiftyLab.HelperCoders\/documentation\/SwiftSyntaxBuilder\/SwiftSyntax\/DoStmtSyntax","fragments":[{"text":"extension","kind":"keyword"},{"kind":"text","text":" "},{"text":"DoStmtSyntax","kind":"identifier","preciseIdentifier":"s:11SwiftSyntax06DoStmtB0V"}],"type":"topic","abstract":[],"url":"\/documentation\/swiftsyntaxbuilder\/swiftsyntax\/dostmtsyntax","navigatorTitle":[{"text":"DoStmtSyntax","kind":"identifier"}],"title":"DoStmtSyntax","role":"symbol"},"doc://com.SwiftyLab.HelperCoders/documentation/SwiftSyntaxBuilder":{"title":"SwiftSyntaxBuilder","type":"topic","url":"\/documentation\/swiftsyntaxbuilder","abstract":[],"role":"collection","identifier":"doc:\/\/com.SwiftyLab.HelperCoders\/documentation\/SwiftSyntaxBuilder","kind":"symbol"},"doc://com.SwiftyLab.HelperCoders/documentation/SwiftSyntaxBuilder/SwiftSyntax/DictionaryElementListSyntax":{"abstract":[],"fragments":[{"kind":"keyword","text":"extension"},{"text":" ","kind":"text"},{"kind":"identifier","text":"DictionaryElementListSyntax","preciseIdentifier":"s:11SwiftSyntax021DictionaryElementListB0V"}],"navigatorTitle":[{"kind":"identifier","text":"DictionaryElementListSyntax"}],"identifier":"doc:\/\/com.SwiftyLab.HelperCoders\/documentation\/SwiftSyntaxBuilder\/SwiftSyntax\/DictionaryElementListSyntax","title":"DictionaryElementListSyntax","type":"topic","role":"symbol","url":"\/documentation\/swiftsyntaxbuilder\/swiftsyntax\/dictionaryelementlistsyntax","kind":"symbol"},"doc://com.SwiftyLab.HelperCoders/documentation/SwiftSyntaxBuilder/SwiftSyntax/TupleExprSyntax":{"identifier":"doc:\/\/com.SwiftyLab.HelperCoders\/documentation\/SwiftSyntaxBuilder\/SwiftSyntax\/TupleExprSyntax","title":"TupleExprSyntax","type":"topic","url":"\/documentation\/swiftsyntaxbuilder\/swiftsyntax\/tupleexprsyntax","role":"symbol","fragments":[{"kind":"keyword","text":"extension"},{"text":" ","kind":"text"},{"kind":"identifier","text":"TupleExprSyntax","preciseIdentifier":"s:11SwiftSyntax09TupleExprB0V"}],"kind":"symbol","abstract":[],"navigatorTitle":[{"kind":"identifier","text":"TupleExprSyntax"}]},"doc://com.SwiftyLab.HelperCoders/documentation/SwiftSyntaxBuilder/SwiftSyntax/EnumCaseDeclSyntax":{"identifier":"doc:\/\/com.SwiftyLab.HelperCoders\/documentation\/SwiftSyntaxBuilder\/SwiftSyntax\/EnumCaseDeclSyntax","fragments":[{"text":"extension","kind":"keyword"},{"kind":"text","text":" "},{"kind":"identifier","preciseIdentifier":"s:11SwiftSyntax012EnumCaseDeclB0V","text":"EnumCaseDeclSyntax"}],"title":"EnumCaseDeclSyntax","abstract":[],"role":"symbol","navigatorTitle":[{"text":"EnumCaseDeclSyntax","kind":"identifier"}],"url":"\/documentation\/swiftsyntaxbuilder\/swiftsyntax\/enumcasedeclsyntax","type":"topic","kind":"symbol"},"doc://com.SwiftyLab.HelperCoders/documentation/SwiftSyntaxBuilder/SwiftSyntax/ActorDeclSyntax":{"identifier":"doc:\/\/com.SwiftyLab.HelperCoders\/documentation\/SwiftSyntaxBuilder\/SwiftSyntax\/ActorDeclSyntax","title":"ActorDeclSyntax","type":"topic","abstract":[],"role":"symbol","url":"\/documentation\/swiftsyntaxbuilder\/swiftsyntax\/actordeclsyntax","fragments":[{"text":"extension","kind":"keyword"},{"kind":"text","text":" "},{"kind":"identifier","preciseIdentifier":"s:11SwiftSyntax09ActorDeclB0V","text":"ActorDeclSyntax"}],"navigatorTitle":[{"text":"ActorDeclSyntax","kind":"identifier"}],"kind":"symbol"},"doc://com.SwiftyLab.HelperCoders/documentation/SwiftSyntaxBuilder/SwiftSyntax/PrimaryAssociatedTypeListSyntax":{"kind":"symbol","type":"topic","url":"\/documentation\/swiftsyntaxbuilder\/swiftsyntax\/primaryassociatedtypelistsyntax","identifier":"doc:\/\/com.SwiftyLab.HelperCoders\/documentation\/SwiftSyntaxBuilder\/SwiftSyntax\/PrimaryAssociatedTypeListSyntax","role":"symbol","title":"PrimaryAssociatedTypeListSyntax","abstract":[],"fragments":[{"kind":"keyword","text":"extension"},{"text":" ","kind":"text"},{"text":"PrimaryAssociatedTypeListSyntax","kind":"identifier","preciseIdentifier":"s:11SwiftSyntax025PrimaryAssociatedTypeListB0V"}],"navigatorTitle":[{"text":"PrimaryAssociatedTypeListSyntax","kind":"identifier"}]},"doc://com.SwiftyLab.HelperCoders/documentation/SwiftSyntaxBuilder/SwiftSyntax/TypeAliasDeclSyntax":{"identifier":"doc:\/\/com.SwiftyLab.HelperCoders\/documentation\/SwiftSyntaxBuilder\/SwiftSyntax\/TypeAliasDeclSyntax","fragments":[{"text":"extension","kind":"keyword"},{"kind":"text","text":" "},{"kind":"identifier","preciseIdentifier":"s:11SwiftSyntax013TypeAliasDeclB0V","text":"TypeAliasDeclSyntax"}],"title":"TypeAliasDeclSyntax","abstract":[],"role":"symbol","navigatorTitle":[{"text":"TypeAliasDeclSyntax","kind":"identifier"}],"url":"\/documentation\/swiftsyntaxbuilder\/swiftsyntax\/typealiasdeclsyntax","type":"topic","kind":"symbol"},"doc://com.SwiftyLab.HelperCoders/documentation/SwiftSyntaxBuilder/SwiftSyntax/TuplePatternSyntax":{"abstract":[],"identifier":"doc:\/\/com.SwiftyLab.HelperCoders\/documentation\/SwiftSyntaxBuilder\/SwiftSyntax\/TuplePatternSyntax","title":"TuplePatternSyntax","url":"\/documentation\/swiftsyntaxbuilder\/swiftsyntax\/tuplepatternsyntax","kind":"symbol","role":"symbol","fragments":[{"text":"extension","kind":"keyword"},{"text":" ","kind":"text"},{"preciseIdentifier":"s:11SwiftSyntax012TuplePatternB0V","text":"TuplePatternSyntax","kind":"identifier"}],"navigatorTitle":[{"kind":"identifier","text":"TuplePatternSyntax"}],"type":"topic"},"doc://com.SwiftyLab.HelperCoders/documentation/SwiftSyntaxBuilder/SwiftSyntax/ProtocolDeclSyntax":{"identifier":"doc:\/\/com.SwiftyLab.HelperCoders\/documentation\/SwiftSyntaxBuilder\/SwiftSyntax\/ProtocolDeclSyntax","fragments":[{"text":"extension","kind":"keyword"},{"kind":"text","text":" "},{"kind":"identifier","preciseIdentifier":"s:11SwiftSyntax012ProtocolDeclB0V","text":"ProtocolDeclSyntax"}],"title":"ProtocolDeclSyntax","abstract":[],"role":"symbol","navigatorTitle":[{"text":"ProtocolDeclSyntax","kind":"identifier"}],"url":"\/documentation\/swiftsyntaxbuilder\/swiftsyntax\/protocoldeclsyntax","type":"topic","kind":"symbol"},"doc://com.SwiftyLab.HelperCoders/documentation/SwiftSyntaxBuilder/SwiftSyntax/ExprListSyntax":{"abstract":[],"title":"ExprListSyntax","kind":"symbol","url":"\/documentation\/swiftsyntaxbuilder\/swiftsyntax\/exprlistsyntax","type":"topic","navigatorTitle":[{"text":"ExprListSyntax","kind":"identifier"}],"role":"symbol","fragments":[{"kind":"keyword","text":"extension"},{"kind":"text","text":" "},{"kind":"identifier","text":"ExprListSyntax","preciseIdentifier":"s:11SwiftSyntax08ExprListB0V"}],"identifier":"doc:\/\/com.SwiftyLab.HelperCoders\/documentation\/SwiftSyntaxBuilder\/SwiftSyntax\/ExprListSyntax"},"doc://com.SwiftyLab.HelperCoders/documentation/SwiftSyntaxBuilder/SwiftSyntax/AccessorDeclListSyntax":{"type":"topic","kind":"symbol","identifier":"doc:\/\/com.SwiftyLab.HelperCoders\/documentation\/SwiftSyntaxBuilder\/SwiftSyntax\/AccessorDeclListSyntax","abstract":[],"title":"AccessorDeclListSyntax","navigatorTitle":[{"kind":"identifier","text":"AccessorDeclListSyntax"}],"url":"\/documentation\/swiftsyntaxbuilder\/swiftsyntax\/accessordecllistsyntax","fragments":[{"text":"extension","kind":"keyword"},{"text":" ","kind":"text"},{"kind":"identifier","text":"AccessorDeclListSyntax","preciseIdentifier":"s:11SwiftSyntax016AccessorDeclListB0V"}],"role":"symbol"},"doc://com.SwiftyLab.HelperCoders/documentation/SwiftSyntaxBuilder/SwiftSyntax/ClosureExprSyntax":{"kind":"symbol","fragments":[{"text":"extension","kind":"keyword"},{"kind":"text","text":" "},{"kind":"identifier","text":"ClosureExprSyntax","preciseIdentifier":"s:11SwiftSyntax011ClosureExprB0V"}],"abstract":[],"url":"\/documentation\/swiftsyntaxbuilder\/swiftsyntax\/closureexprsyntax","title":"ClosureExprSyntax","identifier":"doc:\/\/com.SwiftyLab.HelperCoders\/documentation\/SwiftSyntaxBuilder\/SwiftSyntax\/ClosureExprSyntax","type":"topic","navigatorTitle":[{"kind":"identifier","text":"ClosureExprSyntax"}],"role":"symbol"},"doc://com.SwiftyLab.HelperCoders/documentation/SwiftSyntaxBuilder/SwiftSyntax/FunctionParameterSyntax":{"abstract":[],"identifier":"doc:\/\/com.SwiftyLab.HelperCoders\/documentation\/SwiftSyntaxBuilder\/SwiftSyntax\/FunctionParameterSyntax","kind":"symbol","fragments":[{"text":"extension","kind":"keyword"},{"text":" ","kind":"text"},{"kind":"identifier","text":"FunctionParameterSyntax","preciseIdentifier":"s:11SwiftSyntax017FunctionParameterB0V"}],"type":"topic","url":"\/documentation\/swiftsyntaxbuilder\/swiftsyntax\/functionparametersyntax","title":"FunctionParameterSyntax","role":"symbol","navigatorTitle":[{"kind":"identifier","text":"FunctionParameterSyntax"}]},"doc://com.SwiftyLab.HelperCoders/documentation/SwiftSyntaxBuilder/SwiftSyntax/DeclModifierListSyntax":{"kind":"symbol","type":"topic","url":"\/documentation\/swiftsyntaxbuilder\/swiftsyntax\/declmodifierlistsyntax","identifier":"doc:\/\/com.SwiftyLab.HelperCoders\/documentation\/SwiftSyntaxBuilder\/SwiftSyntax\/DeclModifierListSyntax","role":"symbol","title":"DeclModifierListSyntax","abstract":[],"fragments":[{"kind":"keyword","text":"extension"},{"text":" ","kind":"text"},{"text":"DeclModifierListSyntax","kind":"identifier","preciseIdentifier":"s:11SwiftSyntax016DeclModifierListB0V"}],"navigatorTitle":[{"text":"DeclModifierListSyntax","kind":"identifier"}]},"doc://com.SwiftyLab.HelperCoders/documentation/SwiftSyntaxBuilder/SwiftSyntax/VersionComponentListSyntax":{"abstract":[],"role":"symbol","title":"VersionComponentListSyntax","kind":"symbol","identifier":"doc:\/\/com.SwiftyLab.HelperCoders\/documentation\/SwiftSyntaxBuilder\/SwiftSyntax\/VersionComponentListSyntax","fragments":[{"text":"extension","kind":"keyword"},{"text":" ","kind":"text"},{"kind":"identifier","preciseIdentifier":"s:11SwiftSyntax020VersionComponentListB0V","text":"VersionComponentListSyntax"}],"url":"\/documentation\/swiftsyntaxbuilder\/swiftsyntax\/versioncomponentlistsyntax","navigatorTitle":[{"kind":"identifier","text":"VersionComponentListSyntax"}],"type":"topic"},"doc://com.SwiftyLab.HelperCoders/documentation/SwiftSyntaxBuilder/SwiftSyntax/ExtensionDeclSyntax":{"identifier":"doc:\/\/com.SwiftyLab.HelperCoders\/documentation\/SwiftSyntaxBuilder\/SwiftSyntax\/ExtensionDeclSyntax","title":"ExtensionDeclSyntax","type":"topic","abstract":[],"role":"symbol","url":"\/documentation\/swiftsyntaxbuilder\/swiftsyntax\/extensiondeclsyntax","fragments":[{"text":"extension","kind":"keyword"},{"kind":"text","text":" "},{"kind":"identifier","text":"ExtensionDeclSyntax","preciseIdentifier":"s:11SwiftSyntax013ExtensionDeclB0V"}],"navigatorTitle":[{"text":"ExtensionDeclSyntax","kind":"identifier"}],"kind":"symbol"},"doc://com.SwiftyLab.HelperCoders/documentation/SwiftSyntaxBuilder/SwiftSyntax/FunctionParameterListSyntax":{"kind":"symbol","role":"symbol","navigatorTitle":[{"text":"FunctionParameterListSyntax","kind":"identifier"}],"url":"\/documentation\/swiftsyntaxbuilder\/swiftsyntax\/functionparameterlistsyntax","fragments":[{"text":"extension","kind":"keyword"},{"kind":"text","text":" "},{"text":"FunctionParameterListSyntax","kind":"identifier","preciseIdentifier":"s:11SwiftSyntax021FunctionParameterListB0V"}],"abstract":[],"identifier":"doc:\/\/com.SwiftyLab.HelperCoders\/documentation\/SwiftSyntaxBuilder\/SwiftSyntax\/FunctionParameterListSyntax","type":"topic","title":"FunctionParameterListSyntax"},"doc://com.SwiftyLab.HelperCoders/documentation/SwiftSyntaxBuilder/SwiftSyntax/ClassDeclSyntax":{"url":"\/documentation\/swiftsyntaxbuilder\/swiftsyntax\/classdeclsyntax","kind":"symbol","role":"symbol","navigatorTitle":[{"kind":"identifier","text":"ClassDeclSyntax"}],"title":"ClassDeclSyntax","abstract":[],"fragments":[{"text":"extension","kind":"keyword"},{"text":" ","kind":"text"},{"kind":"identifier","text":"ClassDeclSyntax","preciseIdentifier":"s:11SwiftSyntax09ClassDeclB0V"}],"identifier":"doc:\/\/com.SwiftyLab.HelperCoders\/documentation\/SwiftSyntaxBuilder\/SwiftSyntax\/ClassDeclSyntax","type":"topic"},"doc://com.SwiftyLab.HelperCoders/documentation/SwiftSyntaxBuilder/SwiftSyntax/CodeBlockItemListSyntax":{"title":"CodeBlockItemListSyntax","kind":"symbol","fragments":[{"text":"extension","kind":"keyword"},{"text":" ","kind":"text"},{"preciseIdentifier":"s:11SwiftSyntax017CodeBlockItemListB0V","text":"CodeBlockItemListSyntax","kind":"identifier"}],"abstract":[],"url":"\/documentation\/swiftsyntaxbuilder\/swiftsyntax\/codeblockitemlistsyntax","identifier":"doc:\/\/com.SwiftyLab.HelperCoders\/documentation\/SwiftSyntaxBuilder\/SwiftSyntax\/CodeBlockItemListSyntax","type":"topic","role":"symbol","navigatorTitle":[{"kind":"identifier","text":"CodeBlockItemListSyntax"}]},"doc://com.SwiftyLab.HelperCoders/documentation/SwiftSyntaxBuilder/SwiftSyntax/PrecedenceGroupAttributeListSyntax":{"navigatorTitle":[{"text":"PrecedenceGroupAttributeListSyntax","kind":"identifier"}],"kind":"symbol","type":"topic","title":"PrecedenceGroupAttributeListSyntax","role":"symbol","fragments":[{"text":"extension","kind":"keyword"},{"text":" ","kind":"text"},{"text":"PrecedenceGroupAttributeListSyntax","kind":"identifier","preciseIdentifier":"s:11SwiftSyntax028PrecedenceGroupAttributeListB0V"}],"abstract":[],"url":"\/documentation\/swiftsyntaxbuilder\/swiftsyntax\/precedencegroupattributelistsyntax","identifier":"doc:\/\/com.SwiftyLab.HelperCoders\/documentation\/SwiftSyntaxBuilder\/SwiftSyntax\/PrecedenceGroupAttributeListSyntax"},"doc://com.SwiftyLab.HelperCoders/documentation/SwiftSyntaxBuilder/SwiftSyntax/CodeBlockSyntax":{"abstract":[],"kind":"symbol","type":"topic","title":"CodeBlockSyntax","identifier":"doc:\/\/com.SwiftyLab.HelperCoders\/documentation\/SwiftSyntaxBuilder\/SwiftSyntax\/CodeBlockSyntax","role":"symbol","url":"\/documentation\/swiftsyntaxbuilder\/swiftsyntax\/codeblocksyntax","fragments":[{"text":"extension","kind":"keyword"},{"text":" ","kind":"text"},{"text":"CodeBlockSyntax","kind":"identifier","preciseIdentifier":"s:11SwiftSyntax09CodeBlockB0V"}],"navigatorTitle":[{"kind":"identifier","text":"CodeBlockSyntax"}]},"doc://com.SwiftyLab.HelperCoders/documentation/SwiftSyntaxBuilder/SwiftSyntax/ArrayElementListSyntax":{"type":"topic","kind":"symbol","fragments":[{"text":"extension","kind":"keyword"},{"kind":"text","text":" "},{"preciseIdentifier":"s:11SwiftSyntax016ArrayElementListB0V","kind":"identifier","text":"ArrayElementListSyntax"}],"role":"symbol","title":"ArrayElementListSyntax","identifier":"doc:\/\/com.SwiftyLab.HelperCoders\/documentation\/SwiftSyntaxBuilder\/SwiftSyntax\/ArrayElementListSyntax","navigatorTitle":[{"text":"ArrayElementListSyntax","kind":"identifier"}],"url":"\/documentation\/swiftsyntaxbuilder\/swiftsyntax\/arrayelementlistsyntax","abstract":[]},"doc://com.SwiftyLab.HelperCoders/documentation/SwiftSyntaxBuilder/SwiftSyntax/ClosureCaptureListSyntax":{"identifier":"doc:\/\/com.SwiftyLab.HelperCoders\/documentation\/SwiftSyntaxBuilder\/SwiftSyntax\/ClosureCaptureListSyntax","type":"topic","navigatorTitle":[{"kind":"identifier","text":"ClosureCaptureListSyntax"}],"fragments":[{"text":"extension","kind":"keyword"},{"kind":"text","text":" "},{"text":"ClosureCaptureListSyntax","kind":"identifier","preciseIdentifier":"s:11SwiftSyntax018ClosureCaptureListB0V"}],"role":"symbol","title":"ClosureCaptureListSyntax","url":"\/documentation\/swiftsyntaxbuilder\/swiftsyntax\/closurecapturelistsyntax","abstract":[],"kind":"symbol"},"doc://com.SwiftyLab.HelperCoders/documentation/SwiftSyntaxBuilder/SwiftSyntax/BinaryOperatorExprSyntax":{"type":"topic","title":"BinaryOperatorExprSyntax","fragments":[{"kind":"keyword","text":"extension"},{"text":" ","kind":"text"},{"text":"BinaryOperatorExprSyntax","kind":"identifier","preciseIdentifier":"s:11SwiftSyntax018BinaryOperatorExprB0V"}],"role":"symbol","navigatorTitle":[{"text":"BinaryOperatorExprSyntax","kind":"identifier"}],"identifier":"doc:\/\/com.SwiftyLab.HelperCoders\/documentation\/SwiftSyntaxBuilder\/SwiftSyntax\/BinaryOperatorExprSyntax","url":"\/documentation\/swiftsyntaxbuilder\/swiftsyntax\/binaryoperatorexprsyntax","kind":"symbol","abstract":[]},"doc://com.SwiftyLab.HelperCoders/documentation/SwiftSyntaxBuilder/SwiftSyntax/GenericRequirementListSyntax":{"url":"\/documentation\/swiftsyntaxbuilder\/swiftsyntax\/genericrequirementlistsyntax","title":"GenericRequirementListSyntax","abstract":[],"kind":"symbol","role":"symbol","type":"topic","navigatorTitle":[{"text":"GenericRequirementListSyntax","kind":"identifier"}],"identifier":"doc:\/\/com.SwiftyLab.HelperCoders\/documentation\/SwiftSyntaxBuilder\/SwiftSyntax\/GenericRequirementListSyntax","fragments":[{"text":"extension","kind":"keyword"},{"text":" ","kind":"text"},{"kind":"identifier","text":"GenericRequirementListSyntax","preciseIdentifier":"s:11SwiftSyntax022GenericRequirementListB0V"}]},"doc://com.SwiftyLab.HelperCoders/documentation/SwiftSyntaxBuilder/SwiftSyntax/DocumentationAttributeArgumentListSyntax":{"abstract":[],"identifier":"doc:\/\/com.SwiftyLab.HelperCoders\/documentation\/SwiftSyntaxBuilder\/SwiftSyntax\/DocumentationAttributeArgumentListSyntax","title":"DocumentationAttributeArgumentListSyntax","url":"\/documentation\/swiftsyntaxbuilder\/swiftsyntax\/documentationattributeargumentlistsyntax","kind":"symbol","role":"symbol","fragments":[{"text":"extension","kind":"keyword"},{"text":" ","kind":"text"},{"preciseIdentifier":"s:11SwiftSyntax034DocumentationAttributeArgumentListB0V","text":"DocumentationAttributeArgumentListSyntax","kind":"identifier"}],"navigatorTitle":[{"kind":"identifier","text":"DocumentationAttributeArgumentListSyntax"}],"type":"topic"},"doc://com.SwiftyLab.HelperCoders/documentation/SwiftSyntaxBuilder/SwiftSyntax/ClosureShorthandParameterListSyntax":{"url":"\/documentation\/swiftsyntaxbuilder\/swiftsyntax\/closureshorthandparameterlistsyntax","identifier":"doc:\/\/com.SwiftyLab.HelperCoders\/documentation\/SwiftSyntaxBuilder\/SwiftSyntax\/ClosureShorthandParameterListSyntax","title":"ClosureShorthandParameterListSyntax","kind":"symbol","type":"topic","role":"symbol","navigatorTitle":[{"text":"ClosureShorthandParameterListSyntax","kind":"identifier"}],"abstract":[],"fragments":[{"text":"extension","kind":"keyword"},{"kind":"text","text":" "},{"kind":"identifier","text":"ClosureShorthandParameterListSyntax","preciseIdentifier":"s:11SwiftSyntax029ClosureShorthandParameterListB0V"}]},"doc://com.SwiftyLab.HelperCoders/documentation/SwiftSyntaxBuilder/SwiftSyntax/FunctionCallExprSyntax":{"fragments":[{"kind":"keyword","text":"extension"},{"text":" ","kind":"text"},{"preciseIdentifier":"s:11SwiftSyntax016FunctionCallExprB0V","text":"FunctionCallExprSyntax","kind":"identifier"}],"abstract":[],"navigatorTitle":[{"kind":"identifier","text":"FunctionCallExprSyntax"}],"url":"\/documentation\/swiftsyntaxbuilder\/swiftsyntax\/functioncallexprsyntax","identifier":"doc:\/\/com.SwiftyLab.HelperCoders\/documentation\/SwiftSyntaxBuilder\/SwiftSyntax\/FunctionCallExprSyntax","type":"topic","kind":"symbol","role":"symbol","title":"FunctionCallExprSyntax"},"doc://com.SwiftyLab.HelperCoders/documentation/SwiftSyntaxBuilder/SwiftSyntax/LabeledExprListSyntax":{"identifier":"doc:\/\/com.SwiftyLab.HelperCoders\/documentation\/SwiftSyntaxBuilder\/SwiftSyntax\/LabeledExprListSyntax","abstract":[],"fragments":[{"text":"extension","kind":"keyword"},{"kind":"text","text":" "},{"text":"LabeledExprListSyntax","kind":"identifier","preciseIdentifier":"s:11SwiftSyntax015LabeledExprListB0V"}],"kind":"symbol","url":"\/documentation\/swiftsyntaxbuilder\/swiftsyntax\/labeledexprlistsyntax","type":"topic","navigatorTitle":[{"text":"LabeledExprListSyntax","kind":"identifier"}],"role":"symbol","title":"LabeledExprListSyntax"},"doc://com.SwiftyLab.HelperCoders/documentation/SwiftSyntaxBuilder/SwiftSyntax/MacroDeclSyntax":{"identifier":"doc:\/\/com.SwiftyLab.HelperCoders\/documentation\/SwiftSyntaxBuilder\/SwiftSyntax\/MacroDeclSyntax","title":"MacroDeclSyntax","type":"topic","abstract":[],"role":"symbol","url":"\/documentation\/swiftsyntaxbuilder\/swiftsyntax\/macrodeclsyntax","fragments":[{"text":"extension","kind":"keyword"},{"kind":"text","text":" "},{"kind":"identifier","text":"MacroDeclSyntax","preciseIdentifier":"s:11SwiftSyntax09MacroDeclB0V"}],"navigatorTitle":[{"text":"MacroDeclSyntax","kind":"identifier"}],"kind":"symbol"},"doc://com.SwiftyLab.HelperCoders/documentation/SwiftSyntaxBuilder/SwiftSyntax/GenericParameterClauseSyntax":{"title":"GenericParameterClauseSyntax","navigatorTitle":[{"text":"GenericParameterClauseSyntax","kind":"identifier"}],"identifier":"doc:\/\/com.SwiftyLab.HelperCoders\/documentation\/SwiftSyntaxBuilder\/SwiftSyntax\/GenericParameterClauseSyntax","role":"symbol","abstract":[],"fragments":[{"text":"extension","kind":"keyword"},{"text":" ","kind":"text"},{"preciseIdentifier":"s:11SwiftSyntax022GenericParameterClauseB0V","text":"GenericParameterClauseSyntax","kind":"identifier"}],"type":"topic","url":"\/documentation\/swiftsyntaxbuilder\/swiftsyntax\/genericparameterclausesyntax","kind":"symbol"},"doc://com.SwiftyLab.HelperCoders/documentation/SwiftSyntaxBuilder/SwiftSyntax/UnexpectedNodesSyntax":{"url":"\/documentation\/swiftsyntaxbuilder\/swiftsyntax\/unexpectednodessyntax","type":"topic","title":"UnexpectedNodesSyntax","fragments":[{"text":"extension","kind":"keyword"},{"kind":"text","text":" "},{"preciseIdentifier":"s:11SwiftSyntax015UnexpectedNodesB0V","text":"UnexpectedNodesSyntax","kind":"identifier"}],"kind":"symbol","identifier":"doc:\/\/com.SwiftyLab.HelperCoders\/documentation\/SwiftSyntaxBuilder\/SwiftSyntax\/UnexpectedNodesSyntax","abstract":[],"role":"symbol","navigatorTitle":[{"kind":"identifier","text":"UnexpectedNodesSyntax"}]},"doc://com.SwiftyLab.HelperCoders/documentation/SwiftSyntaxBuilder/SwiftSyntax/ConditionElementListSyntax":{"identifier":"doc:\/\/com.SwiftyLab.HelperCoders\/documentation\/SwiftSyntaxBuilder\/SwiftSyntax\/ConditionElementListSyntax","title":"ConditionElementListSyntax","type":"topic","url":"\/documentation\/swiftsyntaxbuilder\/swiftsyntax\/conditionelementlistsyntax","abstract":[],"kind":"symbol","role":"symbol","fragments":[{"kind":"keyword","text":"extension"},{"kind":"text","text":" "},{"kind":"identifier","preciseIdentifier":"s:11SwiftSyntax020ConditionElementListB0V","text":"ConditionElementListSyntax"}],"navigatorTitle":[{"kind":"identifier","text":"ConditionElementListSyntax"}]},"doc://com.SwiftyLab.HelperCoders/documentation/SwiftSyntaxBuilder/SwiftSyntax/AvailabilityArgumentListSyntax":{"identifier":"doc:\/\/com.SwiftyLab.HelperCoders\/documentation\/SwiftSyntaxBuilder\/SwiftSyntax\/AvailabilityArgumentListSyntax","type":"topic","title":"AvailabilityArgumentListSyntax","kind":"symbol","role":"symbol","url":"\/documentation\/swiftsyntaxbuilder\/swiftsyntax\/availabilityargumentlistsyntax","abstract":[],"fragments":[{"kind":"keyword","text":"extension"},{"text":" ","kind":"text"},{"preciseIdentifier":"s:11SwiftSyntax024AvailabilityArgumentListB0V","text":"AvailabilityArgumentListSyntax","kind":"identifier"}],"navigatorTitle":[{"text":"AvailabilityArgumentListSyntax","kind":"identifier"}]},"doc://com.SwiftyLab.HelperCoders/documentation/SwiftSyntaxBuilder/SwiftSyntax/InheritedTypeListSyntax":{"type":"topic","identifier":"doc:\/\/com.SwiftyLab.HelperCoders\/documentation\/SwiftSyntaxBuilder\/SwiftSyntax\/InheritedTypeListSyntax","role":"symbol","fragments":[{"kind":"keyword","text":"extension"},{"kind":"text","text":" "},{"text":"InheritedTypeListSyntax","preciseIdentifier":"s:11SwiftSyntax017InheritedTypeListB0V","kind":"identifier"}],"abstract":[],"navigatorTitle":[{"kind":"identifier","text":"InheritedTypeListSyntax"}],"title":"InheritedTypeListSyntax","kind":"symbol","url":"\/documentation\/swiftsyntaxbuilder\/swiftsyntax\/inheritedtypelistsyntax"},"doc://com.SwiftyLab.HelperCoders/documentation/SwiftSyntaxBuilder/SwiftSyntax/StructDeclSyntax":{"type":"topic","fragments":[{"kind":"keyword","text":"extension"},{"text":" ","kind":"text"},{"text":"StructDeclSyntax","kind":"identifier","preciseIdentifier":"s:11SwiftSyntax010StructDeclB0V"}],"abstract":[],"kind":"symbol","navigatorTitle":[{"text":"StructDeclSyntax","kind":"identifier"}],"role":"symbol","url":"\/documentation\/swiftsyntaxbuilder\/swiftsyntax\/structdeclsyntax","title":"StructDeclSyntax","identifier":"doc:\/\/com.SwiftyLab.HelperCoders\/documentation\/SwiftSyntaxBuilder\/SwiftSyntax\/StructDeclSyntax"},"doc://com.SwiftyLab.HelperCoders/documentation/SwiftSyntaxBuilder/SwiftSyntax/DeinitializerDeclSyntax":{"identifier":"doc:\/\/com.SwiftyLab.HelperCoders\/documentation\/SwiftSyntaxBuilder\/SwiftSyntax\/DeinitializerDeclSyntax","fragments":[{"text":"extension","kind":"keyword"},{"kind":"text","text":" "},{"kind":"identifier","preciseIdentifier":"s:11SwiftSyntax017DeinitializerDeclB0V","text":"DeinitializerDeclSyntax"}],"title":"DeinitializerDeclSyntax","abstract":[],"role":"symbol","navigatorTitle":[{"text":"DeinitializerDeclSyntax","kind":"identifier"}],"url":"\/documentation\/swiftsyntaxbuilder\/swiftsyntax\/deinitializerdeclsyntax","type":"topic","kind":"symbol"},"doc://com.SwiftyLab.HelperCoders/documentation/SwiftSyntaxBuilder/SwiftSyntax/FunctionParameterClauseSyntax":{"fragments":[{"kind":"keyword","text":"extension"},{"text":" ","kind":"text"},{"preciseIdentifier":"s:11SwiftSyntax023FunctionParameterClauseB0V","text":"FunctionParameterClauseSyntax","kind":"identifier"}],"type":"topic","abstract":[],"navigatorTitle":[{"text":"FunctionParameterClauseSyntax","kind":"identifier"}],"url":"\/documentation\/swiftsyntaxbuilder\/swiftsyntax\/functionparameterclausesyntax","kind":"symbol","role":"symbol","identifier":"doc:\/\/com.SwiftyLab.HelperCoders\/documentation\/SwiftSyntaxBuilder\/SwiftSyntax\/FunctionParameterClauseSyntax","title":"FunctionParameterClauseSyntax"},"doc://com.SwiftyLab.HelperCoders/documentation/SwiftSyntaxBuilder/SwiftSyntax/MacroExpansionExprSyntax":{"role":"symbol","url":"\/documentation\/swiftsyntaxbuilder\/swiftsyntax\/macroexpansionexprsyntax","type":"topic","identifier":"doc:\/\/com.SwiftyLab.HelperCoders\/documentation\/SwiftSyntaxBuilder\/SwiftSyntax\/MacroExpansionExprSyntax","abstract":[],"navigatorTitle":[{"kind":"identifier","text":"MacroExpansionExprSyntax"}],"kind":"symbol","title":"MacroExpansionExprSyntax","fragments":[{"kind":"keyword","text":"extension"},{"text":" ","kind":"text"},{"kind":"identifier","text":"MacroExpansionExprSyntax","preciseIdentifier":"s:11SwiftSyntax018MacroExpansionExprB0V"}]},"doc://com.SwiftyLab.HelperCoders/documentation/SwiftSyntaxBuilder/SwiftSyntax/TupleTypeElementListSyntax":{"kind":"symbol","type":"topic","url":"\/documentation\/swiftsyntaxbuilder\/swiftsyntax\/tupletypeelementlistsyntax","identifier":"doc:\/\/com.SwiftyLab.HelperCoders\/documentation\/SwiftSyntaxBuilder\/SwiftSyntax\/TupleTypeElementListSyntax","role":"symbol","title":"TupleTypeElementListSyntax","abstract":[],"fragments":[{"kind":"keyword","text":"extension"},{"text":" ","kind":"text"},{"text":"TupleTypeElementListSyntax","kind":"identifier","preciseIdentifier":"s:11SwiftSyntax020TupleTypeElementListB0V"}],"navigatorTitle":[{"text":"TupleTypeElementListSyntax","kind":"identifier"}]},"doc://com.SwiftyLab.HelperCoders/documentation/SwiftSyntaxBuilder/SwiftSyntax/CompositionTypeElementListSyntax":{"title":"CompositionTypeElementListSyntax","abstract":[],"role":"symbol","identifier":"doc:\/\/com.SwiftyLab.HelperCoders\/documentation\/SwiftSyntaxBuilder\/SwiftSyntax\/CompositionTypeElementListSyntax","type":"topic","url":"\/documentation\/swiftsyntaxbuilder\/swiftsyntax\/compositiontypeelementlistsyntax","kind":"symbol","navigatorTitle":[{"text":"CompositionTypeElementListSyntax","kind":"identifier"}],"fragments":[{"kind":"keyword","text":"extension"},{"kind":"text","text":" "},{"text":"CompositionTypeElementListSyntax","kind":"identifier","preciseIdentifier":"s:11SwiftSyntax026CompositionTypeElementListB0V"}]},"doc://com.SwiftyLab.HelperCoders/documentation/SwiftSyntaxBuilder/SwiftSyntax/SwitchCaseItemListSyntax":{"kind":"symbol","role":"symbol","identifier":"doc:\/\/com.SwiftyLab.HelperCoders\/documentation\/SwiftSyntaxBuilder\/SwiftSyntax\/SwitchCaseItemListSyntax","url":"\/documentation\/swiftsyntaxbuilder\/swiftsyntax\/switchcaseitemlistsyntax","navigatorTitle":[{"kind":"identifier","text":"SwitchCaseItemListSyntax"}],"abstract":[],"fragments":[{"text":"extension","kind":"keyword"},{"kind":"text","text":" "},{"text":"SwitchCaseItemListSyntax","preciseIdentifier":"s:11SwiftSyntax018SwitchCaseItemListB0V","kind":"identifier"}],"type":"topic","title":"SwitchCaseItemListSyntax"},"doc://com.SwiftyLab.HelperCoders/documentation/SwiftSyntaxBuilder/SwiftSyntax/TypeSpecifierListSyntax":{"type":"topic","abstract":[],"navigatorTitle":[{"kind":"identifier","text":"TypeSpecifierListSyntax"}],"role":"symbol","title":"TypeSpecifierListSyntax","fragments":[{"text":"extension","kind":"keyword"},{"kind":"text","text":" "},{"text":"TypeSpecifierListSyntax","kind":"identifier","preciseIdentifier":"s:11SwiftSyntax017TypeSpecifierListB0V"}],"identifier":"doc:\/\/com.SwiftyLab.HelperCoders\/documentation\/SwiftSyntaxBuilder\/SwiftSyntax\/TypeSpecifierListSyntax","kind":"symbol","url":"\/documentation\/swiftsyntaxbuilder\/swiftsyntax\/typespecifierlistsyntax"},"doc://com.SwiftyLab.HelperCoders/documentation/SwiftSyntaxBuilder/SwiftSyntax/BooleanLiteralExprSyntax":{"url":"\/documentation\/swiftsyntaxbuilder\/swiftsyntax\/booleanliteralexprsyntax","kind":"symbol","identifier":"doc:\/\/com.SwiftyLab.HelperCoders\/documentation\/SwiftSyntaxBuilder\/SwiftSyntax\/BooleanLiteralExprSyntax","abstract":[],"navigatorTitle":[{"text":"BooleanLiteralExprSyntax","kind":"identifier"}],"title":"BooleanLiteralExprSyntax","role":"symbol","type":"topic","fragments":[{"text":"extension","kind":"keyword"},{"text":" ","kind":"text"},{"text":"BooleanLiteralExprSyntax","kind":"identifier","preciseIdentifier":"s:11SwiftSyntax018BooleanLiteralExprB0V"}]},"doc://com.SwiftyLab.HelperCoders/documentation/SwiftSyntaxBuilder/SwiftSyntax/SimpleStringLiteralSegmentListSyntax":{"navigatorTitle":[{"text":"SimpleStringLiteralSegmentListSyntax","kind":"identifier"}],"title":"SimpleStringLiteralSegmentListSyntax","kind":"symbol","type":"topic","role":"symbol","fragments":[{"kind":"keyword","text":"extension"},{"kind":"text","text":" "},{"preciseIdentifier":"s:11SwiftSyntax030SimpleStringLiteralSegmentListB0V","kind":"identifier","text":"SimpleStringLiteralSegmentListSyntax"}],"abstract":[],"url":"\/documentation\/swiftsyntaxbuilder\/swiftsyntax\/simplestringliteralsegmentlistsyntax","identifier":"doc:\/\/com.SwiftyLab.HelperCoders\/documentation\/SwiftSyntaxBuilder\/SwiftSyntax\/SimpleStringLiteralSegmentListSyntax"},"doc://com.SwiftyLab.HelperCoders/documentation/SwiftSyntaxBuilder/SwiftSyntax/PlatformVersionItemListSyntax":{"abstract":[],"identifier":"doc:\/\/com.SwiftyLab.HelperCoders\/documentation\/SwiftSyntaxBuilder\/SwiftSyntax\/PlatformVersionItemListSyntax","title":"PlatformVersionItemListSyntax","url":"\/documentation\/swiftsyntaxbuilder\/swiftsyntax\/platformversionitemlistsyntax","kind":"symbol","role":"symbol","fragments":[{"text":"extension","kind":"keyword"},{"text":" ","kind":"text"},{"preciseIdentifier":"s:11SwiftSyntax023PlatformVersionItemListB0V","text":"PlatformVersionItemListSyntax","kind":"identifier"}],"navigatorTitle":[{"kind":"identifier","text":"PlatformVersionItemListSyntax"}],"type":"topic"},"doc://com.SwiftyLab.HelperCoders/documentation/SwiftSyntaxBuilder/SwiftSyntax/SyntaxProtocol":{"kind":"symbol","type":"topic","url":"\/documentation\/swiftsyntaxbuilder\/swiftsyntax\/syntaxprotocol","identifier":"doc:\/\/com.SwiftyLab.HelperCoders\/documentation\/SwiftSyntaxBuilder\/SwiftSyntax\/SyntaxProtocol","role":"symbol","title":"SyntaxProtocol","abstract":[],"fragments":[{"kind":"keyword","text":"extension"},{"text":" ","kind":"text"},{"text":"SyntaxProtocol","kind":"identifier","preciseIdentifier":"s:11SwiftSyntax0B8ProtocolP"}],"navigatorTitle":[{"text":"SyntaxProtocol","kind":"identifier"}]},"doc://com.SwiftyLab.HelperCoders/documentation/SwiftSyntaxBuilder/SwiftSyntax/ArrayExprSyntax":{"url":"\/documentation\/swiftsyntaxbuilder\/swiftsyntax\/arrayexprsyntax","kind":"symbol","identifier":"doc:\/\/com.SwiftyLab.HelperCoders\/documentation\/SwiftSyntaxBuilder\/SwiftSyntax\/ArrayExprSyntax","type":"topic","title":"ArrayExprSyntax","abstract":[],"role":"symbol","navigatorTitle":[{"kind":"identifier","text":"ArrayExprSyntax"}],"fragments":[{"text":"extension","kind":"keyword"},{"text":" ","kind":"text"},{"kind":"identifier","text":"ArrayExprSyntax","preciseIdentifier":"s:11SwiftSyntax09ArrayExprB0V"}]},"doc://com.SwiftyLab.HelperCoders/documentation/SwiftSyntaxBuilder/SwiftSyntax/GuardStmtSyntax":{"kind":"symbol","type":"topic","identifier":"doc:\/\/com.SwiftyLab.HelperCoders\/documentation\/SwiftSyntaxBuilder\/SwiftSyntax\/GuardStmtSyntax","abstract":[],"role":"symbol","fragments":[{"text":"extension","kind":"keyword"},{"text":" ","kind":"text"},{"preciseIdentifier":"s:11SwiftSyntax09GuardStmtB0V","text":"GuardStmtSyntax","kind":"identifier"}],"navigatorTitle":[{"kind":"identifier","text":"GuardStmtSyntax"}],"title":"GuardStmtSyntax","url":"\/documentation\/swiftsyntaxbuilder\/swiftsyntax\/guardstmtsyntax"},"doc://com.SwiftyLab.HelperCoders/documentation/SwiftSyntaxBuilder/SwiftSyntax/TypeSyntax":{"identifier":"doc:\/\/com.SwiftyLab.HelperCoders\/documentation\/SwiftSyntaxBuilder\/SwiftSyntax\/TypeSyntax","type":"topic","title":"TypeSyntax","abstract":[],"role":"symbol","url":"\/documentation\/swiftsyntaxbuilder\/swiftsyntax\/typesyntax","fragments":[{"kind":"keyword","text":"extension"},{"kind":"text","text":" "},{"text":"TypeSyntax","kind":"identifier","preciseIdentifier":"s:11SwiftSyntax04TypeB0V"}],"navigatorTitle":[{"text":"TypeSyntax","kind":"identifier"}],"kind":"symbol"},"doc://com.SwiftyLab.HelperCoders/documentation/SwiftSyntaxBuilder/SwiftSyntax/InheritanceClauseSyntax":{"type":"topic","navigatorTitle":[{"text":"InheritanceClauseSyntax","kind":"identifier"}],"identifier":"doc:\/\/com.SwiftyLab.HelperCoders\/documentation\/SwiftSyntaxBuilder\/SwiftSyntax\/InheritanceClauseSyntax","kind":"symbol","role":"symbol","title":"InheritanceClauseSyntax","url":"\/documentation\/swiftsyntaxbuilder\/swiftsyntax\/inheritanceclausesyntax","abstract":[],"fragments":[{"text":"extension","kind":"keyword"},{"text":" ","kind":"text"},{"kind":"identifier","preciseIdentifier":"s:11SwiftSyntax017InheritanceClauseB0V","text":"InheritanceClauseSyntax"}]},"doc://com.SwiftyLab.HelperCoders/documentation/SwiftSyntaxBuilder/SwiftSyntax/MultipleTrailingClosureElementListSyntax":{"fragments":[{"kind":"keyword","text":"extension"},{"kind":"text","text":" "},{"kind":"identifier","text":"MultipleTrailingClosureElementListSyntax","preciseIdentifier":"s:11SwiftSyntax034MultipleTrailingClosureElementListB0V"}],"url":"\/documentation\/swiftsyntaxbuilder\/swiftsyntax\/multipletrailingclosureelementlistsyntax","kind":"symbol","identifier":"doc:\/\/com.SwiftyLab.HelperCoders\/documentation\/SwiftSyntaxBuilder\/SwiftSyntax\/MultipleTrailingClosureElementListSyntax","title":"MultipleTrailingClosureElementListSyntax","role":"symbol","navigatorTitle":[{"kind":"identifier","text":"MultipleTrailingClosureElementListSyntax"}],"type":"topic","abstract":[]},"doc://com.SwiftyLab.HelperCoders/documentation/SwiftSyntaxBuilder/SwiftSyntax/IfConfigClauseListSyntax":{"title":"IfConfigClauseListSyntax","url":"\/documentation\/swiftsyntaxbuilder\/swiftsyntax\/ifconfigclauselistsyntax","abstract":[],"kind":"symbol","type":"topic","identifier":"doc:\/\/com.SwiftyLab.HelperCoders\/documentation\/SwiftSyntaxBuilder\/SwiftSyntax\/IfConfigClauseListSyntax","role":"symbol","fragments":[{"kind":"keyword","text":"extension"},{"text":" ","kind":"text"},{"kind":"identifier","preciseIdentifier":"s:11SwiftSyntax018IfConfigClauseListB0V","text":"IfConfigClauseListSyntax"}],"navigatorTitle":[{"text":"IfConfigClauseListSyntax","kind":"identifier"}]},"doc://com.SwiftyLab.HelperCoders/documentation/SwiftSyntaxBuilder/SwiftSyntax/StmtSyntax":{"type":"topic","kind":"symbol","identifier":"doc:\/\/com.SwiftyLab.HelperCoders\/documentation\/SwiftSyntaxBuilder\/SwiftSyntax\/StmtSyntax","title":"StmtSyntax","abstract":[],"navigatorTitle":[{"kind":"identifier","text":"StmtSyntax"}],"url":"\/documentation\/swiftsyntaxbuilder\/swiftsyntax\/stmtsyntax","fragments":[{"text":"extension","kind":"keyword"},{"kind":"text","text":" "},{"kind":"identifier","preciseIdentifier":"s:11SwiftSyntax04StmtB0V","text":"StmtSyntax"}],"role":"symbol"},"doc://com.SwiftyLab.HelperCoders/documentation/SwiftSyntaxBuilder/SwiftSyntax/InitializerDeclSyntax":{"abstract":[],"identifier":"doc:\/\/com.SwiftyLab.HelperCoders\/documentation\/SwiftSyntaxBuilder\/SwiftSyntax\/InitializerDeclSyntax","title":"InitializerDeclSyntax","url":"\/documentation\/swiftsyntaxbuilder\/swiftsyntax\/initializerdeclsyntax","kind":"symbol","role":"symbol","fragments":[{"text":"extension","kind":"keyword"},{"text":" ","kind":"text"},{"preciseIdentifier":"s:11SwiftSyntax015InitializerDeclB0V","text":"InitializerDeclSyntax","kind":"identifier"}],"navigatorTitle":[{"kind":"identifier","text":"InitializerDeclSyntax"}],"type":"topic"},"doc://com.SwiftyLab.HelperCoders/documentation/SwiftSyntaxBuilder/SwiftSyntax/VariableDeclSyntax":{"type":"topic","kind":"symbol","identifier":"doc:\/\/com.SwiftyLab.HelperCoders\/documentation\/SwiftSyntaxBuilder\/SwiftSyntax\/VariableDeclSyntax","url":"\/documentation\/swiftsyntaxbuilder\/swiftsyntax\/variabledeclsyntax","title":"VariableDeclSyntax","role":"symbol","navigatorTitle":[{"kind":"identifier","text":"VariableDeclSyntax"}],"abstract":[],"fragments":[{"text":"extension","kind":"keyword"},{"text":" ","kind":"text"},{"kind":"identifier","preciseIdentifier":"s:11SwiftSyntax012VariableDeclB0V","text":"VariableDeclSyntax"}]},"doc://com.SwiftyLab.HelperCoders/documentation/SwiftSyntaxBuilder/SwiftSyntax/AccessorDeclSyntax":{"abstract":[],"fragments":[{"kind":"keyword","text":"extension"},{"kind":"text","text":" "},{"kind":"identifier","text":"AccessorDeclSyntax","preciseIdentifier":"s:11SwiftSyntax012AccessorDeclB0V"}],"kind":"symbol","title":"AccessorDeclSyntax","url":"\/documentation\/swiftsyntaxbuilder\/swiftsyntax\/accessordeclsyntax","role":"symbol","identifier":"doc:\/\/com.SwiftyLab.HelperCoders\/documentation\/SwiftSyntaxBuilder\/SwiftSyntax\/AccessorDeclSyntax","navigatorTitle":[{"text":"AccessorDeclSyntax","kind":"identifier"}],"type":"topic"},"doc://com.SwiftyLab.HelperCoders/documentation/SwiftSyntaxBuilder/SwiftSyntax/ForStmtSyntax":{"fragments":[{"text":"extension","kind":"keyword"},{"text":" ","kind":"text"},{"preciseIdentifier":"s:11SwiftSyntax07ForStmtB0V","text":"ForStmtSyntax","kind":"identifier"}],"identifier":"doc:\/\/com.SwiftyLab.HelperCoders\/documentation\/SwiftSyntaxBuilder\/SwiftSyntax\/ForStmtSyntax","kind":"symbol","type":"topic","url":"\/documentation\/swiftsyntaxbuilder\/swiftsyntax\/forstmtsyntax","role":"symbol","abstract":[],"navigatorTitle":[{"text":"ForStmtSyntax","kind":"identifier"}],"title":"ForStmtSyntax"},"doc://com.SwiftyLab.HelperCoders/documentation/SwiftSyntaxBuilder/SwiftSyntax/MemberBlockItemListSyntax":{"abstract":[],"identifier":"doc:\/\/com.SwiftyLab.HelperCoders\/documentation\/SwiftSyntaxBuilder\/SwiftSyntax\/MemberBlockItemListSyntax","kind":"symbol","fragments":[{"kind":"keyword","text":"extension"},{"kind":"text","text":" "},{"preciseIdentifier":"s:11SwiftSyntax019MemberBlockItemListB0V","text":"MemberBlockItemListSyntax","kind":"identifier"}],"type":"topic","url":"\/documentation\/swiftsyntaxbuilder\/swiftsyntax\/memberblockitemlistsyntax","title":"MemberBlockItemListSyntax","role":"symbol","navigatorTitle":[{"text":"MemberBlockItemListSyntax","kind":"identifier"}]},"doc://com.SwiftyLab.HelperCoders/documentation/SwiftSyntaxBuilder/SwiftSyntax/SpecializeAttributeArgumentListSyntax":{"title":"SpecializeAttributeArgumentListSyntax","kind":"symbol","abstract":[],"url":"\/documentation\/swiftsyntaxbuilder\/swiftsyntax\/specializeattributeargumentlistsyntax","fragments":[{"text":"extension","kind":"keyword"},{"text":" ","kind":"text"},{"text":"SpecializeAttributeArgumentListSyntax","kind":"identifier","preciseIdentifier":"s:11SwiftSyntax031SpecializeAttributeArgumentListB0V"}],"role":"symbol","type":"topic","identifier":"doc:\/\/com.SwiftyLab.HelperCoders\/documentation\/SwiftSyntaxBuilder\/SwiftSyntax\/SpecializeAttributeArgumentListSyntax","navigatorTitle":[{"kind":"identifier","text":"SpecializeAttributeArgumentListSyntax"}]},"doc://com.SwiftyLab.HelperCoders/documentation/SwiftSyntaxBuilder/SwiftSyntax/LabeledExprSyntax":{"title":"LabeledExprSyntax","type":"topic","url":"\/documentation\/swiftsyntaxbuilder\/swiftsyntax\/labeledexprsyntax","identifier":"doc:\/\/com.SwiftyLab.HelperCoders\/documentation\/SwiftSyntaxBuilder\/SwiftSyntax\/LabeledExprSyntax","kind":"symbol","fragments":[{"text":"extension","kind":"keyword"},{"text":" ","kind":"text"},{"preciseIdentifier":"s:11SwiftSyntax011LabeledExprB0V","kind":"identifier","text":"LabeledExprSyntax"}],"abstract":[],"role":"symbol","navigatorTitle":[{"text":"LabeledExprSyntax","kind":"identifier"}]},"doc://com.SwiftyLab.HelperCoders/documentation/SwiftSyntaxBuilder/SwiftSyntax/WhileStmtSyntax":{"url":"\/documentation\/swiftsyntaxbuilder\/swiftsyntax\/whilestmtsyntax","abstract":[],"fragments":[{"text":"extension","kind":"keyword"},{"text":" ","kind":"text"},{"kind":"identifier","preciseIdentifier":"s:11SwiftSyntax09WhileStmtB0V","text":"WhileStmtSyntax"}],"identifier":"doc:\/\/com.SwiftyLab.HelperCoders\/documentation\/SwiftSyntaxBuilder\/SwiftSyntax\/WhileStmtSyntax","type":"topic","kind":"symbol","navigatorTitle":[{"kind":"identifier","text":"WhileStmtSyntax"}],"role":"symbol","title":"WhileStmtSyntax"},"doc://com.SwiftyLab.HelperCoders/documentation/SwiftSyntaxBuilder/SwiftSyntax/PrecedenceGroupDeclSyntax":{"identifier":"doc:\/\/com.SwiftyLab.HelperCoders\/documentation\/SwiftSyntaxBuilder\/SwiftSyntax\/PrecedenceGroupDeclSyntax","title":"PrecedenceGroupDeclSyntax","type":"topic","abstract":[],"role":"symbol","url":"\/documentation\/swiftsyntaxbuilder\/swiftsyntax\/precedencegroupdeclsyntax","fragments":[{"text":"extension","kind":"keyword"},{"kind":"text","text":" "},{"kind":"identifier","text":"PrecedenceGroupDeclSyntax","preciseIdentifier":"s:11SwiftSyntax019PrecedenceGroupDeclB0V"}],"navigatorTitle":[{"text":"PrecedenceGroupDeclSyntax","kind":"identifier"}],"kind":"symbol"},"doc://com.SwiftyLab.HelperCoders/documentation/SwiftSyntaxBuilder/SwiftSyntax/DesignatedTypeListSyntax":{"title":"DesignatedTypeListSyntax","kind":"symbol","url":"\/documentation\/swiftsyntaxbuilder\/swiftsyntax\/designatedtypelistsyntax","role":"symbol","type":"topic","fragments":[{"text":"extension","kind":"keyword"},{"kind":"text","text":" "},{"kind":"identifier","text":"DesignatedTypeListSyntax","preciseIdentifier":"s:11SwiftSyntax018DesignatedTypeListB0V"}],"abstract":[],"navigatorTitle":[{"text":"DesignatedTypeListSyntax","kind":"identifier"}],"identifier":"doc:\/\/com.SwiftyLab.HelperCoders\/documentation\/SwiftSyntaxBuilder\/SwiftSyntax\/DesignatedTypeListSyntax"},"doc://com.SwiftyLab.HelperCoders/documentation/SwiftSyntaxBuilder/SwiftSyntax/SubscriptCallExprSyntax":{"title":"SubscriptCallExprSyntax","type":"topic","url":"\/documentation\/swiftsyntaxbuilder\/swiftsyntax\/subscriptcallexprsyntax","abstract":[],"identifier":"doc:\/\/com.SwiftyLab.HelperCoders\/documentation\/SwiftSyntaxBuilder\/SwiftSyntax\/SubscriptCallExprSyntax","role":"symbol","fragments":[{"kind":"keyword","text":"extension"},{"text":" ","kind":"text"},{"preciseIdentifier":"s:11SwiftSyntax017SubscriptCallExprB0V","kind":"identifier","text":"SubscriptCallExprSyntax"}],"navigatorTitle":[{"text":"SubscriptCallExprSyntax","kind":"identifier"}],"kind":"symbol"},"doc://com.SwiftyLab.HelperCoders/documentation/SwiftSyntaxBuilder/SwiftSyntax/ClosureCaptureClauseSyntax":{"kind":"symbol","type":"topic","url":"\/documentation\/swiftsyntaxbuilder\/swiftsyntax\/closurecaptureclausesyntax","identifier":"doc:\/\/com.SwiftyLab.HelperCoders\/documentation\/SwiftSyntaxBuilder\/SwiftSyntax\/ClosureCaptureClauseSyntax","role":"symbol","title":"ClosureCaptureClauseSyntax","abstract":[],"fragments":[{"kind":"keyword","text":"extension"},{"text":" ","kind":"text"},{"text":"ClosureCaptureClauseSyntax","kind":"identifier","preciseIdentifier":"s:11SwiftSyntax020ClosureCaptureClauseB0V"}],"navigatorTitle":[{"text":"ClosureCaptureClauseSyntax","kind":"identifier"}]},"doc://com.SwiftyLab.HelperCoders/documentation/SwiftSyntaxBuilder/SwiftSyntax/GenericArgumentClauseSyntax":{"title":"GenericArgumentClauseSyntax","type":"topic","url":"\/documentation\/swiftsyntaxbuilder\/swiftsyntax\/genericargumentclausesyntax","identifier":"doc:\/\/com.SwiftyLab.HelperCoders\/documentation\/SwiftSyntaxBuilder\/SwiftSyntax\/GenericArgumentClauseSyntax","kind":"symbol","fragments":[{"kind":"keyword","text":"extension"},{"kind":"text","text":" "},{"kind":"identifier","preciseIdentifier":"s:11SwiftSyntax021GenericArgumentClauseB0V","text":"GenericArgumentClauseSyntax"}],"abstract":[],"role":"symbol","navigatorTitle":[{"text":"GenericArgumentClauseSyntax","kind":"identifier"}]},"doc://com.SwiftyLab.HelperCoders/documentation/SwiftSyntaxBuilder/SwiftSyntax/DictionaryExprSyntax":{"abstract":[],"identifier":"doc:\/\/com.SwiftyLab.HelperCoders\/documentation\/SwiftSyntaxBuilder\/SwiftSyntax\/DictionaryExprSyntax","title":"DictionaryExprSyntax","url":"\/documentation\/swiftsyntaxbuilder\/swiftsyntax\/dictionaryexprsyntax","kind":"symbol","role":"symbol","fragments":[{"text":"extension","kind":"keyword"},{"text":" ","kind":"text"},{"preciseIdentifier":"s:11SwiftSyntax014DictionaryExprB0V","text":"DictionaryExprSyntax","kind":"identifier"}],"navigatorTitle":[{"kind":"identifier","text":"DictionaryExprSyntax"}],"type":"topic"},"doc://com.SwiftyLab.HelperCoders/documentation/SwiftSyntaxBuilder/SwiftSyntax/SwitchCaseSyntax":{"url":"\/documentation\/swiftsyntaxbuilder\/swiftsyntax\/switchcasesyntax","kind":"symbol","type":"topic","abstract":[],"fragments":[{"text":"extension","kind":"keyword"},{"text":" ","kind":"text"},{"text":"SwitchCaseSyntax","preciseIdentifier":"s:11SwiftSyntax010SwitchCaseB0V","kind":"identifier"}],"role":"symbol","navigatorTitle":[{"text":"SwitchCaseSyntax","kind":"identifier"}],"identifier":"doc:\/\/com.SwiftyLab.HelperCoders\/documentation\/SwiftSyntaxBuilder\/SwiftSyntax\/SwitchCaseSyntax","title":"SwitchCaseSyntax"},"doc://com.SwiftyLab.HelperCoders/documentation/SwiftSyntaxBuilder/SwiftSyntax/StringLiteralExprSyntax":{"identifier":"doc:\/\/com.SwiftyLab.HelperCoders\/documentation\/SwiftSyntaxBuilder\/SwiftSyntax\/StringLiteralExprSyntax","navigatorTitle":[{"text":"StringLiteralExprSyntax","kind":"identifier"}],"role":"symbol","title":"StringLiteralExprSyntax","kind":"symbol","abstract":[],"url":"\/documentation\/swiftsyntaxbuilder\/swiftsyntax\/stringliteralexprsyntax","type":"topic","fragments":[{"kind":"keyword","text":"extension"},{"text":" ","kind":"text"},{"preciseIdentifier":"s:11SwiftSyntax017StringLiteralExprB0V","text":"StringLiteralExprSyntax","kind":"identifier"}]},"doc://com.SwiftyLab.HelperCoders/documentation/SwiftSyntaxBuilder/SwiftSyntax/Trivia":{"type":"topic","role":"symbol","kind":"symbol","abstract":[],"navigatorTitle":[{"kind":"identifier","text":"Trivia"}],"url":"\/documentation\/swiftsyntaxbuilder\/swiftsyntax\/trivia","fragments":[{"text":"extension","kind":"keyword"},{"text":" ","kind":"text"},{"kind":"identifier","text":"Trivia","preciseIdentifier":"s:11SwiftSyntax6TriviaV"}],"title":"Trivia","identifier":"doc:\/\/com.SwiftyLab.HelperCoders\/documentation\/SwiftSyntaxBuilder\/SwiftSyntax\/Trivia"},"doc://com.SwiftyLab.HelperCoders/documentation/SwiftSyntaxBuilder/SwiftSyntax/SubscriptDeclSyntax":{"type":"topic","role":"symbol","navigatorTitle":[{"text":"SubscriptDeclSyntax","kind":"identifier"}],"title":"SubscriptDeclSyntax","fragments":[{"kind":"keyword","text":"extension"},{"text":" ","kind":"text"},{"preciseIdentifier":"s:11SwiftSyntax013SubscriptDeclB0V","kind":"identifier","text":"SubscriptDeclSyntax"}],"identifier":"doc:\/\/com.SwiftyLab.HelperCoders\/documentation\/SwiftSyntaxBuilder\/SwiftSyntax\/SubscriptDeclSyntax","abstract":[],"kind":"symbol","url":"\/documentation\/swiftsyntaxbuilder\/swiftsyntax\/subscriptdeclsyntax"},"doc://com.SwiftyLab.HelperCoders/documentation/SwiftSyntaxBuilder/SwiftSyntax/DeclNameArgumentListSyntax":{"kind":"symbol","type":"topic","url":"\/documentation\/swiftsyntaxbuilder\/swiftsyntax\/declnameargumentlistsyntax","identifier":"doc:\/\/com.SwiftyLab.HelperCoders\/documentation\/SwiftSyntaxBuilder\/SwiftSyntax\/DeclNameArgumentListSyntax","role":"symbol","title":"DeclNameArgumentListSyntax","abstract":[],"fragments":[{"kind":"keyword","text":"extension"},{"text":" ","kind":"text"},{"text":"DeclNameArgumentListSyntax","kind":"identifier","preciseIdentifier":"s:11SwiftSyntax020DeclNameArgumentListB0V"}],"navigatorTitle":[{"text":"DeclNameArgumentListSyntax","kind":"identifier"}]},"doc://com.SwiftyLab.HelperCoders/documentation/SwiftSyntaxBuilder/SwiftSyntax/DeferStmtSyntax":{"abstract":[],"fragments":[{"text":"extension","kind":"keyword"},{"kind":"text","text":" "},{"kind":"identifier","text":"DeferStmtSyntax","preciseIdentifier":"s:11SwiftSyntax09DeferStmtB0V"}],"kind":"symbol","title":"DeferStmtSyntax","url":"\/documentation\/swiftsyntaxbuilder\/swiftsyntax\/deferstmtsyntax","role":"symbol","identifier":"doc:\/\/com.SwiftyLab.HelperCoders\/documentation\/SwiftSyntaxBuilder\/SwiftSyntax\/DeferStmtSyntax","navigatorTitle":[{"text":"DeferStmtSyntax","kind":"identifier"}],"type":"topic"},"doc://com.SwiftyLab.HelperCoders/documentation/SwiftSyntaxBuilder/SwiftSyntax/TokenSyntax":{"url":"\/documentation\/swiftsyntaxbuilder\/swiftsyntax\/tokensyntax","title":"TokenSyntax","role":"symbol","fragments":[{"text":"extension","kind":"keyword"},{"text":" ","kind":"text"},{"text":"TokenSyntax","preciseIdentifier":"s:11SwiftSyntax05TokenB0V","kind":"identifier"}],"kind":"symbol","identifier":"doc:\/\/com.SwiftyLab.HelperCoders\/documentation\/SwiftSyntaxBuilder\/SwiftSyntax\/TokenSyntax","type":"topic","navigatorTitle":[{"text":"TokenSyntax","kind":"identifier"}],"abstract":[]},"doc://com.SwiftyLab.HelperCoders/documentation/SwiftSyntaxBuilder/SwiftSyntax/RepeatStmtSyntax":{"abstract":[],"identifier":"doc:\/\/com.SwiftyLab.HelperCoders\/documentation\/SwiftSyntaxBuilder\/SwiftSyntax\/RepeatStmtSyntax","title":"RepeatStmtSyntax","url":"\/documentation\/swiftsyntaxbuilder\/swiftsyntax\/repeatstmtsyntax","kind":"symbol","role":"symbol","fragments":[{"text":"extension","kind":"keyword"},{"text":" ","kind":"text"},{"preciseIdentifier":"s:11SwiftSyntax010RepeatStmtB0V","text":"RepeatStmtSyntax","kind":"identifier"}],"navigatorTitle":[{"kind":"identifier","text":"RepeatStmtSyntax"}],"type":"topic"},"doc://com.SwiftyLab.HelperCoders/documentation/SwiftSyntaxBuilder/SwiftSyntax/ImportDeclSyntax":{"identifier":"doc:\/\/com.SwiftyLab.HelperCoders\/documentation\/SwiftSyntaxBuilder\/SwiftSyntax\/ImportDeclSyntax","fragments":[{"text":"extension","kind":"keyword"},{"kind":"text","text":" "},{"kind":"identifier","text":"ImportDeclSyntax","preciseIdentifier":"s:11SwiftSyntax010ImportDeclB0V"}],"title":"ImportDeclSyntax","abstract":[],"role":"symbol","navigatorTitle":[{"text":"ImportDeclSyntax","kind":"identifier"}],"url":"\/documentation\/swiftsyntaxbuilder\/swiftsyntax\/importdeclsyntax","type":"topic","kind":"symbol"},"doc://com.SwiftyLab.HelperCoders/documentation/SwiftSyntaxBuilder/SwiftSyntax/KeyPathSubscriptComponentSyntax":{"navigatorTitle":[{"text":"KeyPathSubscriptComponentSyntax","kind":"identifier"}],"identifier":"doc:\/\/com.SwiftyLab.HelperCoders\/documentation\/SwiftSyntaxBuilder\/SwiftSyntax\/KeyPathSubscriptComponentSyntax","title":"KeyPathSubscriptComponentSyntax","type":"topic","role":"symbol","fragments":[{"kind":"keyword","text":"extension"},{"kind":"text","text":" "},{"kind":"identifier","preciseIdentifier":"s:11SwiftSyntax025KeyPathSubscriptComponentB0V","text":"KeyPathSubscriptComponentSyntax"}],"url":"\/documentation\/swiftsyntaxbuilder\/swiftsyntax\/keypathsubscriptcomponentsyntax","kind":"symbol","abstract":[]},"doc://com.SwiftyLab.HelperCoders/documentation/SwiftSyntaxBuilder/SwiftSyntax/AttributeListSyntax":{"type":"topic","role":"symbol","navigatorTitle":[{"text":"AttributeListSyntax","kind":"identifier"}],"title":"AttributeListSyntax","fragments":[{"text":"extension","kind":"keyword"},{"kind":"text","text":" "},{"preciseIdentifier":"s:11SwiftSyntax013AttributeListB0V","text":"AttributeListSyntax","kind":"identifier"}],"identifier":"doc:\/\/com.SwiftyLab.HelperCoders\/documentation\/SwiftSyntaxBuilder\/SwiftSyntax\/AttributeListSyntax","abstract":[],"kind":"symbol","url":"\/documentation\/swiftsyntaxbuilder\/swiftsyntax\/attributelistsyntax"},"doc://com.SwiftyLab.HelperCoders/documentation/SwiftSyntaxBuilder/SwiftSyntax/CatchItemListSyntax":{"fragments":[{"text":"extension","kind":"keyword"},{"kind":"text","text":" "},{"preciseIdentifier":"s:11SwiftSyntax013CatchItemListB0V","text":"CatchItemListSyntax","kind":"identifier"}],"type":"topic","title":"CatchItemListSyntax","abstract":[],"navigatorTitle":[{"kind":"identifier","text":"CatchItemListSyntax"}],"url":"\/documentation\/swiftsyntaxbuilder\/swiftsyntax\/catchitemlistsyntax","kind":"symbol","identifier":"doc:\/\/com.SwiftyLab.HelperCoders\/documentation\/SwiftSyntaxBuilder\/SwiftSyntax\/CatchItemListSyntax","role":"symbol"},"doc://com.SwiftyLab.HelperCoders/documentation/SwiftSyntaxBuilder/SwiftSyntax/EnumCaseParameterSyntax":{"role":"symbol","type":"topic","navigatorTitle":[{"text":"EnumCaseParameterSyntax","kind":"identifier"}],"fragments":[{"kind":"keyword","text":"extension"},{"text":" ","kind":"text"},{"preciseIdentifier":"s:11SwiftSyntax017EnumCaseParameterB0V","text":"EnumCaseParameterSyntax","kind":"identifier"}],"url":"\/documentation\/swiftsyntaxbuilder\/swiftsyntax\/enumcaseparametersyntax","abstract":[],"kind":"symbol","title":"EnumCaseParameterSyntax","identifier":"doc:\/\/com.SwiftyLab.HelperCoders\/documentation\/SwiftSyntaxBuilder\/SwiftSyntax\/EnumCaseParameterSyntax"},"doc://com.SwiftyLab.HelperCoders/documentation/SwiftSyntaxBuilder/SwiftSyntax/WithOptionalCodeBlockSyntax":{"url":"\/documentation\/swiftsyntaxbuilder\/swiftsyntax\/withoptionalcodeblocksyntax","abstract":[],"kind":"symbol","identifier":"doc:\/\/com.SwiftyLab.HelperCoders\/documentation\/SwiftSyntaxBuilder\/SwiftSyntax\/WithOptionalCodeBlockSyntax","fragments":[{"text":"extension","kind":"keyword"},{"text":" ","kind":"text"},{"preciseIdentifier":"s:11SwiftSyntax021WithOptionalCodeBlockB0P","text":"WithOptionalCodeBlockSyntax","kind":"identifier"}],"type":"topic","title":"WithOptionalCodeBlockSyntax","role":"symbol","navigatorTitle":[{"text":"WithOptionalCodeBlockSyntax","kind":"identifier"}]},"doc://com.SwiftyLab.HelperCoders/documentation/SwiftSyntaxBuilder/SwiftSyntax/PrecedenceGroupNameListSyntax":{"abstract":[],"type":"topic","identifier":"doc:\/\/com.SwiftyLab.HelperCoders\/documentation\/SwiftSyntaxBuilder\/SwiftSyntax\/PrecedenceGroupNameListSyntax","title":"PrecedenceGroupNameListSyntax","navigatorTitle":[{"text":"PrecedenceGroupNameListSyntax","kind":"identifier"}],"kind":"symbol","role":"symbol","fragments":[{"text":"extension","kind":"keyword"},{"text":" ","kind":"text"},{"kind":"identifier","preciseIdentifier":"s:11SwiftSyntax023PrecedenceGroupNameListB0V","text":"PrecedenceGroupNameListSyntax"}],"url":"\/documentation\/swiftsyntaxbuilder\/swiftsyntax\/precedencegroupnamelistsyntax"},"doc://com.SwiftyLab.HelperCoders/documentation/SwiftSyntaxBuilder/SwiftSyntax/ExpressionSegmentSyntax":{"role":"symbol","navigatorTitle":[{"kind":"identifier","text":"ExpressionSegmentSyntax"}],"abstract":[],"kind":"symbol","type":"topic","identifier":"doc:\/\/com.SwiftyLab.HelperCoders\/documentation\/SwiftSyntaxBuilder\/SwiftSyntax\/ExpressionSegmentSyntax","fragments":[{"kind":"keyword","text":"extension"},{"kind":"text","text":" "},{"preciseIdentifier":"s:11SwiftSyntax017ExpressionSegmentB0V","text":"ExpressionSegmentSyntax","kind":"identifier"}],"title":"ExpressionSegmentSyntax","url":"\/documentation\/swiftsyntaxbuilder\/swiftsyntax\/expressionsegmentsyntax"},"doc://com.SwiftyLab.HelperCoders/documentation/SwiftSyntaxBuilder/SwiftSyntax/PatternBindingListSyntax":{"identifier":"doc:\/\/com.SwiftyLab.HelperCoders\/documentation\/SwiftSyntaxBuilder\/SwiftSyntax\/PatternBindingListSyntax","type":"topic","title":"PatternBindingListSyntax","url":"\/documentation\/swiftsyntaxbuilder\/swiftsyntax\/patternbindinglistsyntax","role":"symbol","navigatorTitle":[{"text":"PatternBindingListSyntax","kind":"identifier"}],"kind":"symbol","fragments":[{"kind":"keyword","text":"extension"},{"kind":"text","text":" "},{"text":"PatternBindingListSyntax","kind":"identifier","preciseIdentifier":"s:11SwiftSyntax018PatternBindingListB0V"}],"abstract":[]},"doc://com.SwiftyLab.HelperCoders/documentation/SwiftSyntaxBuilder/SwiftSyntax/MemberBlockSyntax":{"type":"topic","fragments":[{"kind":"keyword","text":"extension"},{"kind":"text","text":" "},{"text":"MemberBlockSyntax","preciseIdentifier":"s:11SwiftSyntax011MemberBlockB0V","kind":"identifier"}],"abstract":[],"title":"MemberBlockSyntax","kind":"symbol","navigatorTitle":[{"kind":"identifier","text":"MemberBlockSyntax"}],"role":"symbol","identifier":"doc:\/\/com.SwiftyLab.HelperCoders\/documentation\/SwiftSyntaxBuilder\/SwiftSyntax\/MemberBlockSyntax","url":"\/documentation\/swiftsyntaxbuilder\/swiftsyntax\/memberblocksyntax"},"doc://com.SwiftyLab.HelperCoders/documentation/SwiftSyntaxBuilder/SwiftSyntax/ImportPathComponentListSyntax":{"identifier":"doc:\/\/com.SwiftyLab.HelperCoders\/documentation\/SwiftSyntaxBuilder\/SwiftSyntax\/ImportPathComponentListSyntax","role":"symbol","abstract":[],"type":"topic","title":"ImportPathComponentListSyntax","navigatorTitle":[{"text":"ImportPathComponentListSyntax","kind":"identifier"}],"url":"\/documentation\/swiftsyntaxbuilder\/swiftsyntax\/importpathcomponentlistsyntax","fragments":[{"text":"extension","kind":"keyword"},{"kind":"text","text":" "},{"kind":"identifier","text":"ImportPathComponentListSyntax","preciseIdentifier":"s:11SwiftSyntax023ImportPathComponentListB0V"}],"kind":"symbol"},"doc://com.SwiftyLab.HelperCoders/documentation/SwiftSyntaxBuilder/SwiftSyntax":{"type":"topic","identifier":"doc:\/\/com.SwiftyLab.HelperCoders\/documentation\/SwiftSyntaxBuilder\/SwiftSyntax","kind":"symbol","title":"SwiftSyntax","role":"collection","abstract":[],"url":"\/documentation\/swiftsyntaxbuilder\/swiftsyntax"},"doc://com.SwiftyLab.HelperCoders/documentation/SwiftSyntaxBuilder/SwiftSyntax/KeyPathComponentListSyntax":{"kind":"symbol","type":"topic","url":"\/documentation\/swiftsyntaxbuilder\/swiftsyntax\/keypathcomponentlistsyntax","identifier":"doc:\/\/com.SwiftyLab.HelperCoders\/documentation\/SwiftSyntaxBuilder\/SwiftSyntax\/KeyPathComponentListSyntax","role":"symbol","title":"KeyPathComponentListSyntax","abstract":[],"fragments":[{"kind":"keyword","text":"extension"},{"text":" ","kind":"text"},{"text":"KeyPathComponentListSyntax","kind":"identifier","preciseIdentifier":"s:11SwiftSyntax020KeyPathComponentListB0V"}],"navigatorTitle":[{"text":"KeyPathComponentListSyntax","kind":"identifier"}]},"doc://com.SwiftyLab.HelperCoders/documentation/SwiftSyntaxBuilder/SwiftSyntax/EffectsAttributeArgumentListSyntax":{"abstract":[],"type":"topic","identifier":"doc:\/\/com.SwiftyLab.HelperCoders\/documentation\/SwiftSyntaxBuilder\/SwiftSyntax\/EffectsAttributeArgumentListSyntax","title":"EffectsAttributeArgumentListSyntax","navigatorTitle":[{"kind":"identifier","text":"EffectsAttributeArgumentListSyntax"}],"kind":"symbol","role":"symbol","fragments":[{"kind":"keyword","text":"extension"},{"kind":"text","text":" "},{"kind":"identifier","text":"EffectsAttributeArgumentListSyntax","preciseIdentifier":"s:11SwiftSyntax028EffectsAttributeArgumentListB0V"}],"url":"\/documentation\/swiftsyntaxbuilder\/swiftsyntax\/effectsattributeargumentlistsyntax"},"doc://com.SwiftyLab.HelperCoders/documentation/SwiftSyntaxBuilder/SwiftSyntax/AccessorBlockSyntax":{"kind":"symbol","abstract":[],"navigatorTitle":[{"kind":"identifier","text":"AccessorBlockSyntax"}],"url":"\/documentation\/swiftsyntaxbuilder\/swiftsyntax\/accessorblocksyntax","role":"symbol","identifier":"doc:\/\/com.SwiftyLab.HelperCoders\/documentation\/SwiftSyntaxBuilder\/SwiftSyntax\/AccessorBlockSyntax","title":"AccessorBlockSyntax","type":"topic","fragments":[{"kind":"keyword","text":"extension"},{"kind":"text","text":" "},{"preciseIdentifier":"s:11SwiftSyntax013AccessorBlockB0V","text":"AccessorBlockSyntax","kind":"identifier"}]},"doc://com.SwiftyLab.HelperCoders/documentation/SwiftSyntaxBuilder/SwiftSyntax/GenericParameterListSyntax":{"abstract":[],"role":"symbol","kind":"symbol","identifier":"doc:\/\/com.SwiftyLab.HelperCoders\/documentation\/SwiftSyntaxBuilder\/SwiftSyntax\/GenericParameterListSyntax","title":"GenericParameterListSyntax","fragments":[{"text":"extension","kind":"keyword"},{"kind":"text","text":" "},{"kind":"identifier","preciseIdentifier":"s:11SwiftSyntax020GenericParameterListB0V","text":"GenericParameterListSyntax"}],"url":"\/documentation\/swiftsyntaxbuilder\/swiftsyntax\/genericparameterlistsyntax","navigatorTitle":[{"text":"GenericParameterListSyntax","kind":"identifier"}],"type":"topic"},"doc://com.SwiftyLab.HelperCoders/documentation/SwiftSyntaxBuilder/SwiftSyntax/AssociatedTypeDeclSyntax":{"identifier":"doc:\/\/com.SwiftyLab.HelperCoders\/documentation\/SwiftSyntaxBuilder\/SwiftSyntax\/AssociatedTypeDeclSyntax","fragments":[{"text":"extension","kind":"keyword"},{"kind":"text","text":" "},{"kind":"identifier","text":"AssociatedTypeDeclSyntax","preciseIdentifier":"s:11SwiftSyntax018AssociatedTypeDeclB0V"}],"abstract":[],"title":"AssociatedTypeDeclSyntax","role":"symbol","navigatorTitle":[{"text":"AssociatedTypeDeclSyntax","kind":"identifier"}],"url":"\/documentation\/swiftsyntaxbuilder\/swiftsyntax\/associatedtypedeclsyntax","type":"topic","kind":"symbol"},"doc://com.SwiftyLab.HelperCoders/documentation/SwiftSyntaxBuilder/SwiftSyntax/EnumDeclSyntax":{"identifier":"doc:\/\/com.SwiftyLab.HelperCoders\/documentation\/SwiftSyntaxBuilder\/SwiftSyntax\/EnumDeclSyntax","title":"EnumDeclSyntax","type":"topic","abstract":[],"role":"symbol","url":"\/documentation\/swiftsyntaxbuilder\/swiftsyntax\/enumdeclsyntax","fragments":[{"text":"extension","kind":"keyword"},{"kind":"text","text":" "},{"kind":"identifier","preciseIdentifier":"s:11SwiftSyntax08EnumDeclB0V","text":"EnumDeclSyntax"}],"navigatorTitle":[{"text":"EnumDeclSyntax","kind":"identifier"}],"kind":"symbol"},"doc://com.SwiftyLab.HelperCoders/documentation/SwiftSyntaxBuilder/SwiftSyntax/GenericWhereClauseSyntax":{"abstract":[],"identifier":"doc:\/\/com.SwiftyLab.HelperCoders\/documentation\/SwiftSyntaxBuilder\/SwiftSyntax\/GenericWhereClauseSyntax","title":"GenericWhereClauseSyntax","url":"\/documentation\/swiftsyntaxbuilder\/swiftsyntax\/genericwhereclausesyntax","kind":"symbol","role":"symbol","fragments":[{"text":"extension","kind":"keyword"},{"text":" ","kind":"text"},{"preciseIdentifier":"s:11SwiftSyntax018GenericWhereClauseB0V","text":"GenericWhereClauseSyntax","kind":"identifier"}],"navigatorTitle":[{"kind":"identifier","text":"GenericWhereClauseSyntax"}],"type":"topic"},"doc://com.SwiftyLab.HelperCoders/documentation/SwiftSyntaxBuilder/SwiftSyntax/ClosureParameterSyntax":{"navigatorTitle":[{"text":"ClosureParameterSyntax","kind":"identifier"}],"identifier":"doc:\/\/com.SwiftyLab.HelperCoders\/documentation\/SwiftSyntaxBuilder\/SwiftSyntax\/ClosureParameterSyntax","abstract":[],"type":"topic","fragments":[{"kind":"keyword","text":"extension"},{"kind":"text","text":" "},{"kind":"identifier","preciseIdentifier":"s:11SwiftSyntax016ClosureParameterB0V","text":"ClosureParameterSyntax"}],"url":"\/documentation\/swiftsyntaxbuilder\/swiftsyntax\/closureparametersyntax","kind":"symbol","role":"symbol","title":"ClosureParameterSyntax"},"doc://com.SwiftyLab.HelperCoders/documentation/SwiftSyntaxBuilder/SwiftSyntax/CatchClauseSyntax":{"identifier":"doc:\/\/com.SwiftyLab.HelperCoders\/documentation\/SwiftSyntaxBuilder\/SwiftSyntax\/CatchClauseSyntax","abstract":[],"fragments":[{"kind":"keyword","text":"extension"},{"kind":"text","text":" "},{"preciseIdentifier":"s:11SwiftSyntax011CatchClauseB0V","text":"CatchClauseSyntax","kind":"identifier"}],"kind":"symbol","url":"\/documentation\/swiftsyntaxbuilder\/swiftsyntax\/catchclausesyntax","type":"topic","navigatorTitle":[{"text":"CatchClauseSyntax","kind":"identifier"}],"role":"symbol","title":"CatchClauseSyntax"},"doc://com.SwiftyLab.HelperCoders/documentation/SwiftSyntaxBuilder/SwiftSyntax/ClosureParameterListSyntax":{"kind":"symbol","type":"topic","url":"\/documentation\/swiftsyntaxbuilder\/swiftsyntax\/closureparameterlistsyntax","identifier":"doc:\/\/com.SwiftyLab.HelperCoders\/documentation\/SwiftSyntaxBuilder\/SwiftSyntax\/ClosureParameterListSyntax","role":"symbol","title":"ClosureParameterListSyntax","abstract":[],"fragments":[{"kind":"keyword","text":"extension"},{"text":" ","kind":"text"},{"text":"ClosureParameterListSyntax","kind":"identifier","preciseIdentifier":"s:11SwiftSyntax020ClosureParameterListB0V"}],"navigatorTitle":[{"text":"ClosureParameterListSyntax","kind":"identifier"}]},"doc://com.SwiftyLab.HelperCoders/documentation/SwiftSyntaxBuilder/SwiftSyntax/SourceFileSyntax":{"identifier":"doc:\/\/com.SwiftyLab.HelperCoders\/documentation\/SwiftSyntaxBuilder\/SwiftSyntax\/SourceFileSyntax","abstract":[],"fragments":[{"text":"extension","kind":"keyword"},{"text":" ","kind":"text"},{"kind":"identifier","text":"SourceFileSyntax","preciseIdentifier":"s:11SwiftSyntax010SourceFileB0V"}],"kind":"symbol","url":"\/documentation\/swiftsyntaxbuilder\/swiftsyntax\/sourcefilesyntax","type":"topic","navigatorTitle":[{"kind":"identifier","text":"SourceFileSyntax"}],"role":"symbol","title":"SourceFileSyntax"},"doc://com.SwiftyLab.HelperCoders/documentation/SwiftSyntaxBuilder/SwiftSyntax/SwitchExprSyntax":{"type":"topic","navigatorTitle":[{"text":"SwitchExprSyntax","kind":"identifier"}],"title":"SwitchExprSyntax","identifier":"doc:\/\/com.SwiftyLab.HelperCoders\/documentation\/SwiftSyntaxBuilder\/SwiftSyntax\/SwitchExprSyntax","url":"\/documentation\/swiftsyntaxbuilder\/swiftsyntax\/switchexprsyntax","kind":"symbol","role":"symbol","fragments":[{"kind":"keyword","text":"extension"},{"kind":"text","text":" "},{"text":"SwitchExprSyntax","kind":"identifier","preciseIdentifier":"s:11SwiftSyntax010SwitchExprB0V"}],"abstract":[]},"doc://com.SwiftyLab.HelperCoders/documentation/SwiftSyntaxBuilder/SwiftSyntax/CodeBlockItemSyntax":{"role":"symbol","fragments":[{"kind":"keyword","text":"extension"},{"kind":"text","text":" "},{"kind":"identifier","text":"CodeBlockItemSyntax","preciseIdentifier":"s:11SwiftSyntax013CodeBlockItemB0V"}],"kind":"symbol","navigatorTitle":[{"kind":"identifier","text":"CodeBlockItemSyntax"}],"title":"CodeBlockItemSyntax","abstract":[],"identifier":"doc:\/\/com.SwiftyLab.HelperCoders\/documentation\/SwiftSyntaxBuilder\/SwiftSyntax\/CodeBlockItemSyntax","url":"\/documentation\/swiftsyntaxbuilder\/swiftsyntax\/codeblockitemsyntax","type":"topic"},"doc://com.SwiftyLab.HelperCoders/documentation/SwiftSyntaxBuilder/SwiftSyntax/IfExprSyntax":{"title":"IfExprSyntax","kind":"symbol","navigatorTitle":[{"kind":"identifier","text":"IfExprSyntax"}],"role":"symbol","fragments":[{"kind":"keyword","text":"extension"},{"kind":"text","text":" "},{"kind":"identifier","preciseIdentifier":"s:11SwiftSyntax06IfExprB0V","text":"IfExprSyntax"}],"abstract":[],"identifier":"doc:\/\/com.SwiftyLab.HelperCoders\/documentation\/SwiftSyntaxBuilder\/SwiftSyntax\/IfExprSyntax","url":"\/documentation\/swiftsyntaxbuilder\/swiftsyntax\/ifexprsyntax","type":"topic"},"doc://com.SwiftyLab.HelperCoders/documentation/SwiftSyntaxBuilder/SwiftSyntax/SwitchCaseListSyntax":{"abstract":[],"identifier":"doc:\/\/com.SwiftyLab.HelperCoders\/documentation\/SwiftSyntaxBuilder\/SwiftSyntax\/SwitchCaseListSyntax","title":"SwitchCaseListSyntax","url":"\/documentation\/swiftsyntaxbuilder\/swiftsyntax\/switchcaselistsyntax","kind":"symbol","role":"symbol","fragments":[{"text":"extension","kind":"keyword"},{"text":" ","kind":"text"},{"preciseIdentifier":"s:11SwiftSyntax014SwitchCaseListB0V","text":"SwitchCaseListSyntax","kind":"identifier"}],"navigatorTitle":[{"kind":"identifier","text":"SwitchCaseListSyntax"}],"type":"topic"},"doc://com.SwiftyLab.HelperCoders/documentation/SwiftSyntaxBuilder/SwiftSyntax/GenericArgumentListSyntax":{"kind":"symbol","type":"topic","url":"\/documentation\/swiftsyntaxbuilder\/swiftsyntax\/genericargumentlistsyntax","identifier":"doc:\/\/com.SwiftyLab.HelperCoders\/documentation\/SwiftSyntaxBuilder\/SwiftSyntax\/GenericArgumentListSyntax","role":"symbol","title":"GenericArgumentListSyntax","abstract":[],"fragments":[{"kind":"keyword","text":"extension"},{"text":" ","kind":"text"},{"text":"GenericArgumentListSyntax","kind":"identifier","preciseIdentifier":"s:11SwiftSyntax019GenericArgumentListB0V"}],"navigatorTitle":[{"text":"GenericArgumentListSyntax","kind":"identifier"}]},"doc://com.SwiftyLab.HelperCoders/documentation/SwiftSyntaxBuilder/SwiftSyntax/YieldedExpressionListSyntax":{"url":"\/documentation\/swiftsyntaxbuilder\/swiftsyntax\/yieldedexpressionlistsyntax","identifier":"doc:\/\/com.SwiftyLab.HelperCoders\/documentation\/SwiftSyntaxBuilder\/SwiftSyntax\/YieldedExpressionListSyntax","role":"symbol","navigatorTitle":[{"kind":"identifier","text":"YieldedExpressionListSyntax"}],"fragments":[{"text":"extension","kind":"keyword"},{"text":" ","kind":"text"},{"text":"YieldedExpressionListSyntax","kind":"identifier","preciseIdentifier":"s:11SwiftSyntax021YieldedExpressionListB0V"}],"kind":"symbol","abstract":[],"title":"YieldedExpressionListSyntax","type":"topic"},"doc://com.SwiftyLab.HelperCoders/documentation/SwiftSyntaxBuilder/SwiftSyntax/FunctionDeclSyntax":{"role":"symbol","identifier":"doc:\/\/com.SwiftyLab.HelperCoders\/documentation\/SwiftSyntaxBuilder\/SwiftSyntax\/FunctionDeclSyntax","type":"topic","abstract":[],"navigatorTitle":[{"kind":"identifier","text":"FunctionDeclSyntax"}],"title":"FunctionDeclSyntax","kind":"symbol","fragments":[{"kind":"keyword","text":"extension"},{"kind":"text","text":" "},{"kind":"identifier","text":"FunctionDeclSyntax","preciseIdentifier":"s:11SwiftSyntax012FunctionDeclB0V"}],"url":"\/documentation\/swiftsyntaxbuilder\/swiftsyntax\/functiondeclsyntax"},"doc://com.SwiftyLab.HelperCoders/documentation/SwiftSyntaxBuilder/SwiftSyntax/VersionTupleSyntax":{"abstract":[],"title":"VersionTupleSyntax","kind":"symbol","type":"topic","url":"\/documentation\/swiftsyntaxbuilder\/swiftsyntax\/versiontuplesyntax","role":"symbol","fragments":[{"kind":"keyword","text":"extension"},{"text":" ","kind":"text"},{"text":"VersionTupleSyntax","kind":"identifier","preciseIdentifier":"s:11SwiftSyntax012VersionTupleB0V"}],"navigatorTitle":[{"kind":"identifier","text":"VersionTupleSyntax"}],"identifier":"doc:\/\/com.SwiftyLab.HelperCoders\/documentation\/SwiftSyntaxBuilder\/SwiftSyntax\/VersionTupleSyntax"},"doc://com.SwiftyLab.HelperCoders/documentation/SwiftSyntaxBuilder/SwiftSyntax/IntegerLiteralExprSyntax":{"navigatorTitle":[{"kind":"identifier","text":"IntegerLiteralExprSyntax"}],"type":"topic","role":"symbol","abstract":[],"url":"\/documentation\/swiftsyntaxbuilder\/swiftsyntax\/integerliteralexprsyntax","kind":"symbol","fragments":[{"kind":"keyword","text":"extension"},{"kind":"text","text":" "},{"text":"IntegerLiteralExprSyntax","kind":"identifier","preciseIdentifier":"s:11SwiftSyntax018IntegerLiteralExprB0V"}],"identifier":"doc:\/\/com.SwiftyLab.HelperCoders\/documentation\/SwiftSyntaxBuilder\/SwiftSyntax\/IntegerLiteralExprSyntax","title":"IntegerLiteralExprSyntax"},"doc://com.SwiftyLab.HelperCoders/documentation/SwiftSyntaxBuilder/SwiftSyntax/SequenceExprSyntax":{"abstract":[],"kind":"symbol","title":"SequenceExprSyntax","role":"symbol","url":"\/documentation\/swiftsyntaxbuilder\/swiftsyntax\/sequenceexprsyntax","identifier":"doc:\/\/com.SwiftyLab.HelperCoders\/documentation\/SwiftSyntaxBuilder\/SwiftSyntax\/SequenceExprSyntax","type":"topic","navigatorTitle":[{"text":"SequenceExprSyntax","kind":"identifier"}],"fragments":[{"kind":"keyword","text":"extension"},{"text":" ","kind":"text"},{"preciseIdentifier":"s:11SwiftSyntax012SequenceExprB0V","kind":"identifier","text":"SequenceExprSyntax"}]},"doc://com.SwiftyLab.HelperCoders/documentation/SwiftSyntaxBuilder/SwiftSyntax/SwitchCaseLabelSyntax":{"abstract":[],"identifier":"doc:\/\/com.SwiftyLab.HelperCoders\/documentation\/SwiftSyntaxBuilder\/SwiftSyntax\/SwitchCaseLabelSyntax","title":"SwitchCaseLabelSyntax","url":"\/documentation\/swiftsyntaxbuilder\/swiftsyntax\/switchcaselabelsyntax","kind":"symbol","role":"symbol","fragments":[{"text":"extension","kind":"keyword"},{"text":" ","kind":"text"},{"preciseIdentifier":"s:11SwiftSyntax015SwitchCaseLabelB0V","text":"SwitchCaseLabelSyntax","kind":"identifier"}],"navigatorTitle":[{"kind":"identifier","text":"SwitchCaseLabelSyntax"}],"type":"topic"}}}